{"objective_value": 1866, "events": [{"time": 0, "train": 0, "operation": 0}, {"time": 0, "train": 0, "operation": 1}, {"time": 0, "train": 1, "operation": 0}, {"time": 0, "train": 1, "operation": 1}, {"time": 0, "train": 2, "operation": 0}, {"time": 0, "train": 3, "operation": 0}, {"time": 0, "train": 4, "operation": 0}, {"time": 0, "train": 5, "operation": 0}, {"time": 0, "train": 6, "operation": 0}, {"time": 0, "train": 6, "operation": 1}, {"time": 0, "train": 7, "operation": 0}, {"time": 0, "train": 8, "operation": 0}, {"time": 0, "train": 8, "operation": 1}, {"time": 0, "train": 9, "operation": 0}, {"time": 0, "train": 10, "operation": 0}, {"time": 0, "train": 11, "operation": 0}, {"time": 0, "train": 12, "operation": 0}, {"time": 6, "train": 0, "operation": 2}, {"time": 30, "train": 12, "operation": 1}, {"time": 31, "train": 6, "operation": 2}, {"time": 51, "train": 12, "operation": 2}, {"time": 52, "train": 1, "operation": 2}, {"time": 55, "train": 11, "operation": 1}, {"time": 81, "train": 11, "operation": 2}, {"time": 113, "train": 4, "operation": 1}, {"time": 131, "train": 4, "operation": 2}, {"time": 161, "train": 2, "operation": 1}, {"time": 168, "train": 2, "operation": 2}, {"time": 169, "train": 8, "operation": 2}, {"time": 246, "train": 7, "operation": 1}, {"time": 248, "train": 11, "operation": 3}, {"time": 255, "train": 7, "operation": 2}, {"time": 270, "train": 3, "operation": 1}, {"time": 270, "train": 11, "operation": 4}, {"time": 275, "train": 3, "operation": 2}, {"time": 313, "train": 4, "operation": 3}, {"time": 321, "train": 4, "operation": 4}, {"time": 342, "train": 2, "operation": 3}, {"time": 342, "train": 4, "operation": 5}, {"time": 348, "train": 4, "operation": 6}, {"time": 416, "train": 3, "operation": 3}, {"time": 422, "train": 5, "operation": 1}, {"time": 441, "train": 9, "operation": 1}, {"time": 451, "train": 9, "operation": 2}, {"time": 497, "train": 5, "operation": 2}, {"time": 511, "train": 0, "operation": 3}, {"time": 518, "train": 0, "operation": 4}, {"time": 519, "train": 2, "operation": 4}, {"time": 546, "train": 1, "operation": 4}, {"time": 556, "train": 5, "operation": 3}, {"time": 560, "train": 4, "operation": 7}, {"time": 560, "train": 4, "operation": 8}, {"time": 563, "train": 8, "operation": 3}, {"time": 570, "train": 1, "operation": 6}, {"time": 571, "train": 8, "operation": 5}, {"time": 589, "train": 11, "operation": 6}, {"time": 599, "train": 9, "operation": 3}, {"time": 611, "train": 6, "operation": 3}, {"time": 614, "train": 9, "operation": 4}, {"time": 618, "train": 11, "operation": 8}, {"time": 628, "train": 5, "operation": 4}, {"time": 629, "train": 6, "operation": 4}, {"time": 631, "train": 12, "operation": 3}, {"time": 647, "train": 12, "operation": 4}, {"time": 655, "train": 10, "operation": 1}, {"time": 671, "train": 10, "operation": 2}, {"time": 700, "train": 8, "operation": 7}, {"time": 708, "train": 8, "operation": 9}, {"time": 746, "train": 0, "operation": 6}, {"time": 777, "train": 0, "operation": 8}, {"time": 782, "train": 9, "operation": 5}, {"time": 811, "train": 5, "operation": 5}, {"time": 824, "train": 5, "operation": 6}, {"time": 829, "train": 12, "operation": 5}, {"time": 829, "train": 12, "operation": 6}, {"time": 831, "train": 4, "operation": 9}, {"time": 850, "train": 4, "operation": 10}, {"time": 972, "train": 0, "operation": 11}, {"time": 1000, "train": 0, "operation": 15}, {"time": 1024, "train": 2, "operation": 6}, {"time": 1032, "train": 2, "operation": 8}, {"time": 1080, "train": 12, "operation": 7}, {"time": 1095, "train": 12, "operation": 8}, {"time": 1133, "train": 10, "operation": 3}, {"time": 1140, "train": 10, "operation": 4}, {"time": 1150, "train": 1, "operation": 9}, {"time": 1166, "train": 1, "operation": 12}, {"time": 1175, "train": 7, "operation": 3}, {"time": 1180, "train": 0, "operation": 17}, {"time": 1186, "train": 7, "operation": 4}, {"time": 1187, "train": 3, "operation": 4}, {"time": 1187, "train": 8, "operation": 11}, {"time": 1188, "train": 11, "operation": 10}, {"time": 1196, "train": 8, "operation": 12}, {"time": 1197, "train": 0, "operation": 19}, {"time": 1197, "train": 9, "operation": 6}, {"time": 1197, "train": 11, "operation": 12}, {"time": 1208, "train": 6, "operation": 5}, {"time": 1230, "train": 6, "operation": 6}, {"time": 1235, "train": 2, "operation": 11}, {"time": 1247, "train": 5, "operation": 7}, {"time": 1254, "train": 5, "operation": 8}, {"time": 1266, "train": 2, "operation": 15}, {"time": 1273, "train": 0, "operation": 22}, {"time": 1294, "train": 0, "operation": 26}, {"time": 1348, "train": 1, "operation": 14}, {"time": 1348, "train": 1, "operation": 16}, {"time": 1364, "train": 8, "operation": 13}, {"time": 1379, "train": 8, "operation": 14}, {"time": 1461, "train": 2, "operation": 17}, {"time": 1476, "train": 7, "operation": 5}, {"time": 1487, "train": 7, "operation": 6}, {"time": 1489, "train": 2, "operation": 21}, {"time": 1498, "train": 11, "operation": 13}, {"time": 1508, "train": 11, "operation": 15}, {"time": 1521, "train": 12, "operation": 9}, {"time": 1521, "train": 12, "operation": 10}, {"time": 1527, "train": 8, "operation": 15}, {"time": 1527, "train": 8, "operation": 16}, {"time": 1574, "train": 6, "operation": 7}, {"time": 1574, "train": 6, "operation": 8}, {"time": 1599, "train": 1, "operation": 19}, {"time": 1614, "train": 1, "operation": 22}, {"time": 1627, "train": 4, "operation": 11}, {"time": 1648, "train": 4, "operation": 12}, {"time": 1669, "train": 2, "operation": 25}, {"time": 1670, "train": 11, "operation": 17}, {"time": 1675, "train": 12, "operation": 11}, {"time": 1676, "train": 9, "operation": 7}, {"time": 1679, "train": 11, "operation": 19}, {"time": 1683, "train": 9, "operation": 8}, {"time": 1686, "train": 2, "operation": 27}, {"time": 1690, "train": 12, "operation": 12}, {"time": 1758, "train": 10, "operation": 5}, {"time": 1762, "train": 2, "operation": 29}, {"time": 1764, "train": 10, "operation": 7}, {"time": 1770, "train": 6, "operation": 10}, {"time": 1783, "train": 2, "operation": 33}, {"time": 1785, "train": 0, "operation": 32}, {"time": 1788, "train": 6, "operation": 12}, {"time": 1813, "train": 9, "operation": 9}, {"time": 1816, "train": 0, "operation": 36}, {"time": 1821, "train": 9, "operation": 10}, {"time": 1842, "train": 12, "operation": 13}, {"time": 1850, "train": 12, "operation": 14}, {"time": 1867, "train": 12, "operation": 15}, {"time": 1872, "train": 12, "operation": 16}, {"time": 1953, "train": 11, "operation": 23}, {"time": 1960, "train": 11, "operation": 24}, {"time": 1991, "train": 4, "operation": 13}, {"time": 1991, "train": 4, "operation": 14}, {"time": 2019, "train": 3, "operation": 6}, {"time": 2028, "train": 3, "operation": 8}, {"time": 2040, "train": 1, "operation": 24}, {"time": 2040, "train": 1, "operation": 26}, {"time": 2040, "train": 10, "operation": 9}, {"time": 2048, "train": 10, "operation": 11}, {"time": 2050, "train": 12, "operation": 17}, {"time": 2050, "train": 12, "operation": 18}, {"time": 2094, "train": 5, "operation": 9}, {"time": 2101, "train": 5, "operation": 11}, {"time": 2127, "train": 7, "operation": 7}, {"time": 2133, "train": 7, "operation": 9}, {"time": 2180, "train": 11, "operation": 25}, {"time": 2180, "train": 11, "operation": 26}, {"time": 2194, "train": 1, "operation": 29}, {"time": 2209, "train": 1, "operation": 32}, {"time": 2215, "train": 9, "operation": 11}, {"time": 2222, "train": 9, "operation": 12}, {"time": 2244, "train": 4, "operation": 15}, {"time": 2273, "train": 2, "operation": 37}, {"time": 2275, "train": 12, "operation": 19}, {"time": 2279, "train": 4, "operation": 16}, {"time": 2291, "train": 12, "operation": 20}, {"time": 2297, "train": 5, "operation": 13}, {"time": 2303, "train": 2, "operation": 41}, {"time": 2304, "train": 5, "operation": 15}, {"time": 2329, "train": 7, "operation": 11}, {"time": 2331, "train": 6, "operation": 15}, {"time": 2337, "train": 7, "operation": 13}, {"time": 2340, "train": 6, "operation": 18}, {"time": 2396, "train": 0, "operation": 39}, {"time": 2396, "train": 9, "operation": 13}, {"time": 2402, "train": 9, "operation": 14}, {"time": 2414, "train": 0, "operation": 43}, {"time": 2440, "train": 10, "operation": 14}, {"time": 2451, "train": 10, "operation": 16}, {"time": 2466, "train": 6, "operation": 23}, {"time": 2482, "train": 6, "operation": 28}, {"time": 2562, "train": 1, "operation": 34}, {"time": 2562, "train": 1, "operation": 36}, {"time": 2563, "train": 3, "operation": 12}, {"time": 2579, "train": 3, "operation": 16}, {"time": 2666, "train": 10, "operation": 18}, {"time": 2678, "train": 10, "operation": 20}, {"time": 2703, "train": 4, "operation": 17}, {"time": 2710, "train": 4, "operation": 18}, {"time": 2787, "train": 1, "operation": 39}, {"time": 2789, "train": 10, "operation": 22}, {"time": 2789, "train": 10, "operation": 24}, {"time": 2803, "train": 1, "operation": 42}, {"time": 2838, "train": 4, "operation": 19}, {"time": 2863, "train": 4, "operation": 20}, {"time": 2884, "train": 2, "operation": 46}, {"time": 2902, "train": 2, "operation": 50}, {"time": 2907, "train": 9, "operation": 16}, {"time": 2915, "train": 9, "operation": 18}, {"time": 2957, "train": 5, "operation": 17}, {"time": 2963, "train": 5, "operation": 19}, {"time": 2976, "train": 3, "operation": 18}, {"time": 2981, "train": 12, "operation": 21}, {"time": 2984, "train": 6, "operation": 30}, {"time": 2985, "train": 3, "operation": 20}, {"time": 2993, "train": 0, "operation": 46}, {"time": 2998, "train": 12, "operation": 22}, {"time": 3008, "train": 6, "operation": 32}, {"time": 3015, "train": 0, "operation": 50}, {"time": 3062, "train": 10, "operation": 25}, {"time": 3062, "train": 10, "operation": 26}, {"time": 3108, "train": 4, "operation": 21}, {"time": 3108, "train": 4, "operation": 22}, {"time": 3118, "train": 9, "operation": 21}, {"time": 3149, "train": 9, "operation": 25}, {"time": 3151, "train": 7, "operation": 16}, {"time": 3160, "train": 7, "operation": 18}, {"time": 3161, "train": 5, "operation": 21}, {"time": 3169, "train": 5, "operation": 23}, {"time": 3300, "train": 12, "operation": 23}, {"time": 3300, "train": 12, "operation": 24}, {"time": 3344, "train": 9, "operation": 31}, {"time": 3359, "train": 0, "operation": 54}, {"time": 3359, "train": 0, "operation": 56}, {"time": 3372, "train": 9, "operation": 35}, {"time": 3400, "train": 1, "operation": 45}, {"time": 3417, "train": 1, "operation": 48}, {"time": 3478, "train": 6, "operation": 33}, {"time": 3478, "train": 6, "operation": 34}, {"time": 3481, "train": 2, "operation": 55}, {"time": 3495, "train": 3, "operation": 21}, {"time": 3500, "train": 3, "operation": 22}, {"time": 3503, "train": 2, "operation": 59}, {"time": 3531, "train": 12, "operation": 25}, {"time": 3539, "train": 4, "operation": 23}, {"time": 3550, "train": 7, "operation": 20}, {"time": 3552, "train": 9, "operation": 39}, {"time": 3555, "train": 0, "operation": 60}, {"time": 3558, "train": 4, "operation": 24}, {"time": 3562, "train": 7, "operation": 22}, {"time": 3566, "train": 12, "operation": 26}, {"time": 3569, "train": 9, "operation": 43}, {"time": 3573, "train": 0, "operation": 64}, {"time": 3645, "train": 9, "operation": 50}, {"time": 3666, "train": 9, "operation": 54}, {"time": 3677, "train": 1, "operation": 50}, {"time": 3677, "train": 1, "operation": 52}, {"time": 3696, "train": 3, "operation": 23}, {"time": 3702, "train": 3, "operation": 24}, {"time": 3726, "train": 7, "operation": 24}, {"time": 3768, "train": 6, "operation": 35}, {"time": 3791, "train": 6, "operation": 36}, {"time": 3808, "train": 7, "operation": 25}, {"time": 3808, "train": 7, "operation": 26}, {"time": 3836, "train": 1, "operation": 55}, {"time": 3847, "train": 2, "operation": 61}, {"time": 3847, "train": 2, "operation": 63}, {"time": 3851, "train": 1, "operation": 58}, {"time": 3919, "train": 12, "operation": 27}, {"time": 3924, "train": 12, "operation": 28}, {"time": 3983, "train": 3, "operation": 25}, {"time": 3990, "train": 3, "operation": 27}, {"time": 4032, "train": 12, "operation": 29}, {"time": 4035, "train": 6, "operation": 37}, {"time": 4035, "train": 6, "operation": 38}, {"time": 4043, "train": 2, "operation": 65}, {"time": 4053, "train": 12, "operation": 30}, {"time": 4061, "train": 2, "operation": 67}, {"time": 4116, "train": 0, "operation": 67}, {"time": 4123, "train": 5, "operation": 26}, {"time": 4125, "train": 0, "operation": 70}, {"time": 4132, "train": 5, "operation": 28}, {"time": 4144, "train": 3, "operation": 29}, {"time": 4144, "train": 3, "operation": 31}, {"time": 4164, "train": 4, "operation": 25}, {"time": 4182, "train": 4, "operation": 26}, {"time": 4211, "train": 9, "operation": 60}, {"time": 4242, "train": 9, "operation": 64}, {"time": 4251, "train": 0, "operation": 75}, {"time": 4267, "train": 0, "operation": 80}, {"time": 4274, "train": 12, "operation": 31}, {"time": 4274, "train": 12, "operation": 32}, {"time": 4316, "train": 1, "operation": 61}, {"time": 4337, "train": 1, "operation": 64}, {"time": 4558, "train": 1, "operation": 66}, {"time": 4558, "train": 1, "operation": 68}, {"time": 4604, "train": 2, "operation": 69}, {"time": 4613, "train": 2, "operation": 70}, {"time": 4671, "train": 12, "operation": 33}, {"time": 4687, "train": 12, "operation": 34}, {"time": 4718, "train": 5, "operation": 32}, {"time": 4734, "train": 5, "operation": 36}, {"time": 4739, "train": 2, "operation": 71}, {"time": 4755, "train": 2, "operation": 72}, {"time": 4769, "train": 0, "operation": 82}, {"time": 4787, "train": 4, "operation": 27}, {"time": 4793, "train": 0, "operation": 84}, {"time": 4805, "train": 4, "operation": 28}, {"time": 4822, "train": 9, "operation": 67}, {"time": 4840, "train": 9, "operation": 71}, {"time": 4917, "train": 1, "operation": 71}, {"time": 4933, "train": 1, "operation": 74}, {"time": 5159, "train": 5, "operation": 38}, {"time": 5168, "train": 5, "operation": 40}, {"time": 5257, "train": 2, "operation": 73}, {"time": 5263, "train": 0, "operation": 85}, {"time": 5263, "train": 0, "operation": 86}, {"time": 5281, "train": 2, "operation": 75}, {"time": 5308, "train": 12, "operation": 35}, {"time": 5323, "train": 12, "operation": 36}, {"time": 5338, "train": 4, "operation": 29}, {"time": 5338, "train": 4, "operation": 30}, {"time": 5419, "train": 9, "operation": 74}, {"time": 5438, "train": 1, "operation": 77}, {"time": 5441, "train": 9, "operation": 78}, {"time": 5454, "train": 1, "operation": 80}, {"time": 5553, "train": 0, "operation": 87}, {"time": 5576, "train": 0, "operation": 89}, {"time": 5751, "train": 2, "operation": 77}, {"time": 5751, "train": 2, "operation": 79}, {"time": 5780, "train": 5, "operation": 41}, {"time": 5785, "train": 9, "operation": 82}, {"time": 5785, "train": 9, "operation": 84}, {"time": 5786, "train": 5, "operation": 43}, {"time": 5820, "train": 0, "operation": 91}, {"time": 5856, "train": 0, "operation": 94}, {"time": 5866, "train": 12, "operation": 37}, {"time": 5881, "train": 12, "operation": 38}, {"time": 5934, "train": 0, "operation": 97}, {"time": 5943, "train": 0, "operation": 100}, {"time": 5957, "train": 1, "operation": 82}, {"time": 5981, "train": 9, "operation": 88}, {"time": 5999, "train": 9, "operation": 92}, {"time": 6036, "train": 0, "operation": 111}, {"time": 6041, "train": 2, "operation": 81}, {"time": 6056, "train": 0, "operation": 115}, {"time": 6059, "train": 2, "operation": 85}, {"time": 6062, "train": 5, "operation": 45}, {"time": 6070, "train": 5, "operation": 47}, {"time": 6077, "train": 0, "operation": 119}, {"time": 6111, "train": 0, "operation": 125}, {"time": 6160, "train": 0, "operation": 131}, {"time": 6167, "train": 0, "operation": 141}, {"time": 6187, "train": 0, "operation": 148}, {"time": 6252, "train": 0, "operation": 155}, {"time": 6273, "train": 0, "operation": 162}, {"time": 6284, "train": 0, "operation": 177}, {"time": 6303, "train": 2, "operation": 90}, {"time": 6326, "train": 12, "operation": 39}, {"time": 6326, "train": 12, "operation": 40}, {"time": 6327, "train": 1, "operation": 84}, {"time": 6339, "train": 2, "operation": 94}, {"time": 6405, "train": 0, "operation": 181}, {"time": 6417, "train": 2, "operation": 97}, {"time": 6426, "train": 2, "operation": 100}, {"time": 6457, "train": 0, "operation": 193}, {"time": 6462, "train": 5, "operation": 50}, {"time": 6473, "train": 5, "operation": 52}, {"time": 6512, "train": 0, "operation": 211}, {"time": 6519, "train": 2, "operation": 111}, {"time": 6539, "train": 2, "operation": 115}, {"time": 6542, "train": 9, "operation": 94}, {"time": 6551, "train": 9, "operation": 96}, {"time": 6556, "train": 0, "operation": 223}, {"time": 6560, "train": 2, "operation": 119}, {"time": 6566, "train": 0, "operation": 236}, {"time": 6594, "train": 2, "operation": 125}, {"time": 6640, "train": 0, "operation": 248}, {"time": 6643, "train": 2, "operation": 131}, {"time": 6650, "train": 2, "operation": 141}, {"time": 6660, "train": 0, "operation": 262}, {"time": 6660, "train": 0, "operation": 286}, {"time": 6670, "train": 2, "operation": 148}, {"time": 6677, "train": 9, "operation": 98}, {"time": 6688, "train": 5, "operation": 54}, {"time": 6693, "train": 9, "operation": 100}, {"time": 6700, "train": 5, "operation": 56}, {"time": 6735, "train": 2, "operation": 155}, {"time": 6756, "train": 2, "operation": 162}, {"time": 6767, "train": 2, "operation": 177}, {"time": 6772, "train": 1, "operation": 91}, {"time": 6772, "train": 1, "operation": 92}, {"time": 6811, "train": 5, "operation": 58}, {"time": 6811, "train": 5, "operation": 60}, {"time": 6888, "train": 2, "operation": 181}, {"time": 6940, "train": 2, "operation": 193}, {"time": 6995, "train": 2, "operation": 211}, {"time": 7039, "train": 2, "operation": 223}, {"time": 7049, "train": 2, "operation": 236}, {"time": 7084, "train": 5, "operation": 61}, {"time": 7084, "train": 5, "operation": 62}, {"time": 7123, "train": 2, "operation": 248}, {"time": 7143, "train": 2, "operation": 262}, {"time": 7143, "train": 2, "operation": 286}, {"time": 7195, "train": 9, "operation": 102}, {"time": 7219, "train": 9, "operation": 104}, {"time": 7689, "train": 9, "operation": 106}, {"time": 7689, "train": 9, "operation": 108}, {"time": 7979, "train": 9, "operation": 111}, {"time": 8002, "train": 9, "operation": 115}, {"time": 8246, "train": 9, "operation": 118}, {"time": 8282, "train": 9, "operation": 121}, {"time": 8360, "train": 9, "operation": 124}, {"time": 8369, "train": 9, "operation": 127}, {"time": 8462, "train": 9, "operation": 129}, {"time": 8482, "train": 9, "operation": 132}, {"time": 8503, "train": 9, "operation": 141}, {"time": 8537, "train": 9, "operation": 144}, {"time": 8586, "train": 9, "operation": 147}, {"time": 8593, "train": 9, "operation": 156}, {"time": 8613, "train": 9, "operation": 165}, {"time": 8678, "train": 9, "operation": 176}, {"time": 8699, "train": 9, "operation": 187}, {"time": 8710, "train": 9, "operation": 206}, {"time": 8831, "train": 9, "operation": 228}, {"time": 8883, "train": 9, "operation": 265}, {"time": 8947, "train": 9, "operation": 298}, {"time": 8955, "train": 9, "operation": 343}, {"time": 8992, "train": 9, "operation": 370}, {"time": 9023, "train": 9, "operation": 407}, {"time": 9246, "train": 9, "operation": 436}, {"time": 9308, "train": 9, "operation": 453}, {"time": 9427, "train": 9, "operation": 455}, {"time": 9440, "train": 9, "operation": 457}, {"time": 9459, "train": 9, "operation": 459}, {"time": 9459, "train": 9, "operation": 461}, {"time": 9478, "train": 9, "operation": 463}, {"time": 9478, "train": 9, "operation": 465}]}