{"objective_value": 114336, "events": [{"time": 0, "train": 0, "operation": 0}, {"time": 0, "train": 0, "operation": 1}, {"time": 0, "train": 1, "operation": 0}, {"time": 0, "train": 1, "operation": 1}, {"time": 0, "train": 2, "operation": 0}, {"time": 0, "train": 3, "operation": 0}, {"time": 0, "train": 4, "operation": 0}, {"time": 0, "train": 5, "operation": 0}, {"time": 0, "train": 6, "operation": 0}, {"time": 0, "train": 7, "operation": 0}, {"time": 0, "train": 8, "operation": 0}, {"time": 0, "train": 9, "operation": 0}, {"time": 0, "train": 10, "operation": 0}, {"time": 0, "train": 11, "operation": 0}, {"time": 0, "train": 12, "operation": 0}, {"time": 0, "train": 13, "operation": 0}, {"time": 0, "train": 14, "operation": 0}, {"time": 0, "train": 15, "operation": 0}, {"time": 0, "train": 16, "operation": 0}, {"time": 0, "train": 17, "operation": 0}, {"time": 0, "train": 18, "operation": 0}, {"time": 0, "train": 19, "operation": 0}, {"time": 0, "train": 20, "operation": 0}, {"time": 0, "train": 21, "operation": 0}, {"time": 0, "train": 22, "operation": 0}, {"time": 0, "train": 23, "operation": 0}, {"time": 0, "train": 24, "operation": 0}, {"time": 0, "train": 25, "operation": 0}, {"time": 0, "train": 26, "operation": 0}, {"time": 0, "train": 27, "operation": 0}, {"time": 0, "train": 28, "operation": 0}, {"time": 0, "train": 29, "operation": 0}, {"time": 8, "train": 0, "operation": 2}, {"time": 111, "train": 2, "operation": 1}, {"time": 157, "train": 3, "operation": 1}, {"time": 159, "train": 3, "operation": 3}, {"time": 167, "train": 2, "operation": 2}, {"time": 173, "train": 3, "operation": 4}, {"time": 189, "train": 4, "operation": 1}, {"time": 201, "train": 4, "operation": 3}, {"time": 213, "train": 6, "operation": 1}, {"time": 286, "train": 7, "operation": 1}, {"time": 288, "train": 7, "operation": 2}, {"time": 366, "train": 0, "operation": 3}, {"time": 427, "train": 6, "operation": 3}, {"time": 492, "train": 8, "operation": 1}, {"time": 514, "train": 4, "operation": 4}, {"time": 533, "train": 9, "operation": 1}, {"time": 557, "train": 7, "operation": 5}, {"time": 559, "train": 7, "operation": 6}, {"time": 570, "train": 0, "operation": 11}, {"time": 613, "train": 8, "operation": 3}, {"time": 623, "train": 10, "operation": 1}, {"time": 668, "train": 9, "operation": 3}, {"time": 669, "train": 11, "operation": 1}, {"time": 764, "train": 2, "operation": 4}, {"time": 788, "train": 10, "operation": 3}, {"time": 838, "train": 12, "operation": 1}, {"time": 874, "train": 3, "operation": 5}, {"time": 876, "train": 3, "operation": 6}, {"time": 912, "train": 11, "operation": 3}, {"time": 959, "train": 13, "operation": 2}, {"time": 999, "train": 2, "operation": 5}, {"time": 1006, "train": 6, "operation": 5}, {"time": 1019, "train": 12, "operation": 3}, {"time": 1036, "train": 14, "operation": 2}, {"time": 1068, "train": 7, "operation": 7}, {"time": 1070, "train": 7, "operation": 9}, {"time": 1105, "train": 12, "operation": 4}, {"time": 1187, "train": 6, "operation": 6}, {"time": 1192, "train": 2, "operation": 7}, {"time": 1192, "train": 4, "operation": 5}, {"time": 1206, "train": 0, "operation": 13}, {"time": 1296, "train": 1, "operation": 3}, {"time": 1306, "train": 4, "operation": 7}, {"time": 1307, "train": 14, "operation": 3}, {"time": 1329, "train": 13, "operation": 3}, {"time": 1387, "train": 8, "operation": 4}, {"time": 1389, "train": 7, "operation": 11}, {"time": 1527, "train": 11, "operation": 4}, {"time": 1563, "train": 2, "operation": 10}, {"time": 1565, "train": 2, "operation": 11}, {"time": 1578, "train": 9, "operation": 5}, {"time": 1636, "train": 10, "operation": 4}, {"time": 1639, "train": 3, "operation": 8}, {"time": 1645, "train": 11, "operation": 6}, {"time": 1665, "train": 15, "operation": 1}, {"time": 1667, "train": 15, "operation": 2}, {"time": 1686, "train": 15, "operation": 3}, {"time": 1692, "train": 8, "operation": 6}, {"time": 1701, "train": 11, "operation": 7}, {"time": 1783, "train": 1, "operation": 4}, {"time": 1794, "train": 9, "operation": 6}, {"time": 1812, "train": 4, "operation": 8}, {"time": 1831, "train": 7, "operation": 13}, {"time": 1832, "train": 12, "operation": 5}, {"time": 1887, "train": 10, "operation": 5}, {"time": 1932, "train": 6, "operation": 7}, {"time": 1980, "train": 15, "operation": 5}, {"time": 1982, "train": 12, "operation": 7}, {"time": 1991, "train": 15, "operation": 6}, {"time": 2024, "train": 15, "operation": 7}, {"time": 2028, "train": 2, "operation": 19}, {"time": 2030, "train": 2, "operation": 20}, {"time": 2035, "train": 4, "operation": 10}, {"time": 2055, "train": 6, "operation": 9}, {"time": 2080, "train": 7, "operation": 14}, {"time": 2187, "train": 10, "operation": 6}, {"time": 2208, "train": 3, "operation": 9}, {"time": 2219, "train": 11, "operation": 9}, {"time": 2228, "train": 0, "operation": 14}, {"time": 2260, "train": 14, "operation": 4}, {"time": 2401, "train": 2, "operation": 25}, {"time": 2401, "train": 14, "operation": 6}, {"time": 2405, "train": 10, "operation": 7}, {"time": 2422, "train": 13, "operation": 5}, {"time": 2433, "train": 4, "operation": 11}, {"time": 2435, "train": 4, "operation": 12}, {"time": 2444, "train": 11, "operation": 10}, {"time": 2513, "train": 15, "operation": 8}, {"time": 2553, "train": 12, "operation": 8}, {"time": 2590, "train": 8, "operation": 8}, {"time": 2601, "train": 13, "operation": 6}, {"time": 2642, "train": 9, "operation": 7}, {"time": 2674, "train": 4, "operation": 15}, {"time": 2676, "train": 4, "operation": 16}, {"time": 2678, "train": 7, "operation": 15}, {"time": 2684, "train": 11, "operation": 12}, {"time": 2699, "train": 15, "operation": 10}, {"time": 2720, "train": 2, "operation": 26}, {"time": 2734, "train": 1, "operation": 6}, {"time": 2734, "train": 12, "operation": 16}, {"time": 2767, "train": 8, "operation": 9}, {"time": 2800, "train": 7, "operation": 17}, {"time": 2857, "train": 9, "operation": 9}, {"time": 2865, "train": 6, "operation": 10}, {"time": 2958, "train": 1, "operation": 7}, {"time": 2992, "train": 10, "operation": 8}, {"time": 3015, "train": 12, "operation": 18}, {"time": 3038, "train": 6, "operation": 12}, {"time": 3041, "train": 11, "operation": 15}, {"time": 3043, "train": 11, "operation": 16}, {"time": 3103, "train": 8, "operation": 11}, {"time": 3124, "train": 0, "operation": 15}, {"time": 3140, "train": 0, "operation": 16}, {"time": 3141, "train": 4, "operation": 17}, {"time": 3142, "train": 16, "operation": 1}, {"time": 3143, "train": 4, "operation": 19}, {"time": 3183, "train": 16, "operation": 2}, {"time": 3272, "train": 10, "operation": 10}, {"time": 3314, "train": 0, "operation": 18}, {"time": 3330, "train": 8, "operation": 12}, {"time": 3408, "train": 2, "operation": 27}, {"time": 3429, "train": 4, "operation": 21}, {"time": 3502, "train": 11, "operation": 24}, {"time": 3504, "train": 11, "operation": 25}, {"time": 3539, "train": 10, "operation": 11}, {"time": 3541, "train": 10, "operation": 12}, {"time": 3565, "train": 14, "operation": 7}, {"time": 3592, "train": 16, "operation": 3}, {"time": 3602, "train": 3, "operation": 11}, {"time": 3612, "train": 13, "operation": 8}, {"time": 3715, "train": 14, "operation": 9}, {"time": 3746, "train": 16, "operation": 5}, {"time": 3780, "train": 4, "operation": 22}, {"time": 3830, "train": 1, "operation": 9}, {"time": 3837, "train": 6, "operation": 13}, {"time": 3840, "train": 9, "operation": 11}, {"time": 3858, "train": 13, "operation": 12}, {"time": 3875, "train": 11, "operation": 30}, {"time": 3919, "train": 8, "operation": 14}, {"time": 3932, "train": 4, "operation": 24}, {"time": 3938, "train": 15, "operation": 11}, {"time": 3984, "train": 10, "operation": 13}, {"time": 3986, "train": 10, "operation": 15}, {"time": 3998, "train": 2, "operation": 29}, {"time": 4019, "train": 9, "operation": 12}, {"time": 4066, "train": 14, "operation": 11}, {"time": 4067, "train": 7, "operation": 18}, {"time": 4100, "train": 8, "operation": 15}, {"time": 4189, "train": 11, "operation": 31}, {"time": 4220, "train": 15, "operation": 13}, {"time": 4226, "train": 7, "operation": 20}, {"time": 4236, "train": 6, "operation": 15}, {"time": 4247, "train": 17, "operation": 1}, {"time": 4277, "train": 17, "operation": 2}, {"time": 4282, "train": 0, "operation": 20}, {"time": 4328, "train": 16, "operation": 6}, {"time": 4440, "train": 0, "operation": 21}, {"time": 4458, "train": 2, "operation": 30}, {"time": 4458, "train": 13, "operation": 17}, {"time": 4497, "train": 4, "operation": 26}, {"time": 4563, "train": 2, "operation": 32}, {"time": 4564, "train": 16, "operation": 8}, {"time": 4567, "train": 13, "operation": 23}, {"time": 4576, "train": 13, "operation": 27}, {"time": 4581, "train": 17, "operation": 4}, {"time": 4681, "train": 4, "operation": 27}, {"time": 4776, "train": 17, "operation": 5}, {"time": 4814, "train": 11, "operation": 32}, {"time": 4837, "train": 8, "operation": 16}, {"time": 4896, "train": 2, "operation": 33}, {"time": 4898, "train": 2, "operation": 34}, {"time": 4929, "train": 11, "operation": 34}, {"time": 4944, "train": 13, "operation": 31}, {"time": 4951, "train": 8, "operation": 18}, {"time": 4963, "train": 9, "operation": 14}, {"time": 4983, "train": 7, "operation": 21}, {"time": 5113, "train": 7, "operation": 23}, {"time": 5130, "train": 13, "operation": 41}, {"time": 5139, "train": 2, "operation": 37}, {"time": 5141, "train": 2, "operation": 38}, {"time": 5142, "train": 4, "operation": 28}, {"time": 5176, "train": 0, "operation": 22}, {"time": 5180, "train": 6, "operation": 17}, {"time": 5209, "train": 9, "operation": 19}, {"time": 5210, "train": 3, "operation": 12}, {"time": 5255, "train": 17, "operation": 7}, {"time": 5340, "train": 9, "operation": 24}, {"time": 5359, "train": 6, "operation": 18}, {"time": 5379, "train": 4, "operation": 30}, {"time": 5431, "train": 15, "operation": 14}, {"time": 5433, "train": 0, "operation": 24}, {"time": 5435, "train": 11, "operation": 35}, {"time": 5464, "train": 10, "operation": 16}, {"time": 5550, "train": 11, "operation": 37}, {"time": 5572, "train": 14, "operation": 12}, {"time": 5596, "train": 15, "operation": 16}, {"time": 5597, "train": 9, "operation": 27}, {"time": 5603, "train": 2, "operation": 39}, {"time": 5605, "train": 2, "operation": 41}, {"time": 5701, "train": 8, "operation": 19}, {"time": 5740, "train": 16, "operation": 9}, {"time": 5757, "train": 13, "operation": 42}, {"time": 5777, "train": 9, "operation": 30}, {"time": 5804, "train": 0, "operation": 25}, {"time": 5836, "train": 8, "operation": 21}, {"time": 5884, "train": 2, "operation": 43}, {"time": 5903, "train": 0, "operation": 26}, {"time": 5903, "train": 0, "operation": 27}, {"time": 5911, "train": 7, "operation": 24}, {"time": 5912, "train": 11, "operation": 38}, {"time": 5914, "train": 11, "operation": 39}, {"time": 5930, "train": 13, "operation": 44}, {"time": 6013, "train": 6, "operation": 20}, {"time": 6027, "train": 4, "operation": 31}, {"time": 6034, "train": 16, "operation": 11}, {"time": 6047, "train": 7, "operation": 26}, {"time": 6136, "train": 17, "operation": 8}, {"time": 6175, "train": 11, "operation": 42}, {"time": 6177, "train": 11, "operation": 43}, {"time": 6213, "train": 2, "operation": 44}, {"time": 6239, "train": 14, "operation": 13}, {"time": 6259, "train": 6, "operation": 25}, {"time": 6297, "train": 3, "operation": 13}, {"time": 6307, "train": 4, "operation": 33}, {"time": 6310, "train": 10, "operation": 17}, {"time": 6312, "train": 10, "operation": 18}, {"time": 6353, "train": 2, "operation": 46}, {"time": 6377, "train": 9, "operation": 37}, {"time": 6383, "train": 14, "operation": 15}, {"time": 6394, "train": 6, "operation": 30}, {"time": 6558, "train": 9, "operation": 47}, {"time": 6669, "train": 3, "operation": 15}, {"time": 6678, "train": 8, "operation": 23}, {"time": 6685, "train": 11, "operation": 44}, {"time": 6688, "train": 11, "operation": 46}, {"time": 6846, "train": 17, "operation": 10}, {"time": 6875, "train": 16, "operation": 12}, {"time": 6876, "train": 2, "operation": 48}, {"time": 6899, "train": 13, "operation": 45}, {"time": 6916, "train": 13, "operation": 47}, {"time": 6954, "train": 8, "operation": 24}, {"time": 6981, "train": 11, "operation": 48}, {"time": 6998, "train": 4, "operation": 34}, {"time": 7009, "train": 15, "operation": 18}, {"time": 7021, "train": 16, "operation": 14}, {"time": 7060, "train": 2, "operation": 49}, {"time": 7069, "train": 7, "operation": 28}, {"time": 7076, "train": 10, "operation": 19}, {"time": 7076, "train": 16, "operation": 15}, {"time": 7090, "train": 9, "operation": 48}, {"time": 7227, "train": 7, "operation": 29}, {"time": 7271, "train": 17, "operation": 11}, {"time": 7295, "train": 9, "operation": 50}, {"time": 7307, "train": 11, "operation": 49}, {"time": 7355, "train": 6, "operation": 33}, {"time": 7420, "train": 14, "operation": 16}, {"time": 7438, "train": 10, "operation": 21}, {"time": 7440, "train": 11, "operation": 51}, {"time": 7465, "train": 4, "operation": 36}, {"time": 7529, "train": 2, "operation": 50}, {"time": 7534, "train": 6, "operation": 36}, {"time": 7617, "train": 7, "operation": 30}, {"time": 7668, "train": 2, "operation": 52}, {"time": 7758, "train": 3, "operation": 20}, {"time": 7760, "train": 3, "operation": 21}, {"time": 7783, "train": 7, "operation": 32}, {"time": 7813, "train": 8, "operation": 26}, {"time": 7816, "train": 13, "operation": 48}, {"time": 7893, "train": 17, "operation": 12}, {"time": 7931, "train": 11, "operation": 52}, {"time": 7992, "train": 8, "operation": 27}, {"time": 8001, "train": 17, "operation": 14}, {"time": 8025, "train": 11, "operation": 54}, {"time": 8078, "train": 16, "operation": 16}, {"time": 8100, "train": 9, "operation": 51}, {"time": 8134, "train": 6, "operation": 43}, {"time": 8212, "train": 9, "operation": 53}, {"time": 8322, "train": 6, "operation": 53}, {"time": 8328, "train": 2, "operation": 54}, {"time": 8347, "train": 4, "operation": 38}, {"time": 8434, "train": 16, "operation": 18}, {"time": 8461, "train": 11, "operation": 55}, {"time": 8463, "train": 7, "operation": 34}, {"time": 8474, "train": 17, "operation": 15}, {"time": 8505, "train": 4, "operation": 39}, {"time": 8644, "train": 7, "operation": 35}, {"time": 8679, "train": 8, "operation": 28}, {"time": 8688, "train": 16, "operation": 19}, {"time": 8724, "train": 11, "operation": 57}, {"time": 8771, "train": 13, "operation": 49}, {"time": 8772, "train": 8, "operation": 29}, {"time": 8834, "train": 4, "operation": 40}, {"time": 8857, "train": 1, "operation": 10}, {"time": 8883, "train": 10, "operation": 23}, {"time": 8903, "train": 6, "operation": 54}, {"time": 8922, "train": 13, "operation": 51}, {"time": 8940, "train": 17, "operation": 17}, {"time": 8976, "train": 4, "operation": 42}, {"time": 9009, "train": 8, "operation": 30}, {"time": 9063, "train": 6, "operation": 56}, {"time": 9067, "train": 16, "operation": 22}, {"time": 9077, "train": 3, "operation": 29}, {"time": 9085, "train": 3, "operation": 31}, {"time": 9109, "train": 16, "operation": 26}, {"time": 9144, "train": 17, "operation": 18}, {"time": 9147, "train": 10, "operation": 24}, {"time": 9167, "train": 9, "operation": 54}, {"time": 9168, "train": 12, "operation": 20}, {"time": 9274, "train": 12, "operation": 21}, {"time": 9274, "train": 12, "operation": 22}, {"time": 9281, "train": 11, "operation": 58}, {"time": 9313, "train": 17, "operation": 20}, {"time": 9335, "train": 16, "operation": 28}, {"time": 9374, "train": 11, "operation": 60}, {"time": 9381, "train": 12, "operation": 23}, {"time": 9463, "train": 3, "operation": 32}, {"time": 9474, "train": 1, "operation": 11}, {"time": 9491, "train": 7, "operation": 36}, {"time": 9514, "train": 16, "operation": 29}, {"time": 9554, "train": 4, "operation": 44}, {"time": 9606, "train": 16, "operation": 31}, {"time": 9609, "train": 8, "operation": 31}, {"time": 9612, "train": 1, "operation": 13}, {"time": 9621, "train": 7, "operation": 38}, {"time": 9649, "train": 13, "operation": 52}, {"time": 9669, "train": 17, "operation": 23}, {"time": 9671, "train": 17, "operation": 24}, {"time": 9728, "train": 8, "operation": 32}, {"time": 9737, "train": 8, "operation": 33}, {"time": 9887, "train": 4, "operation": 45}, {"time": 9903, "train": 13, "operation": 54}, {"time": 9965, "train": 6, "operation": 57}, {"time": 9968, "train": 11, "operation": 61}, {"time": 9981, "train": 6, "operation": 59}, {"time": 10042, "train": 9, "operation": 55}, {"time": 10067, "train": 11, "operation": 63}, {"time": 10088, "train": 17, "operation": 32}, {"time": 10090, "train": 17, "operation": 34}, {"time": 10101, "train": 17, "operation": 35}, {"time": 10105, "train": 8, "operation": 34}, {"time": 10172, "train": 9, "operation": 57}, {"time": 10250, "train": 3, "operation": 33}, {"time": 10260, "train": 13, "operation": 55}, {"time": 10294, "train": 10, "operation": 25}, {"time": 10309, "train": 12, "operation": 25}, {"time": 10316, "train": 8, "operation": 42}, {"time": 10336, "train": 1, "operation": 14}, {"time": 10364, "train": 2, "operation": 55}, {"time": 10416, "train": 13, "operation": 57}, {"time": 10426, "train": 17, "operation": 36}, {"time": 10438, "train": 6, "operation": 60}, {"time": 10488, "train": 12, "operation": 26}, {"time": 10516, "train": 7, "operation": 39}, {"time": 10534, "train": 1, "operation": 16}, {"time": 10564, "train": 3, "operation": 34}, {"time": 10610, "train": 4, "operation": 46}, {"time": 10671, "train": 7, "operation": 41}, {"time": 10679, "train": 10, "operation": 27}, {"time": 10813, "train": 9, "operation": 58}, {"time": 10822, "train": 16, "operation": 35}, {"time": 10901, "train": 11, "operation": 65}, {"time": 10912, "train": 4, "operation": 48}, {"time": 10955, "train": 1, "operation": 18}, {"time": 10965, "train": 8, "operation": 43}, {"time": 11012, "train": 3, "operation": 36}, {"time": 11042, "train": 9, "operation": 60}, {"time": 11059, "train": 11, "operation": 66}, {"time": 11067, "train": 2, "operation": 56}, {"time": 11075, "train": 17, "operation": 38}, {"time": 11142, "train": 1, "operation": 20}, {"time": 11144, "train": 1, "operation": 21}, {"time": 11145, "train": 8, "operation": 45}, {"time": 11297, "train": 2, "operation": 58}, {"time": 11342, "train": 11, "operation": 67}, {"time": 11365, "train": 9, "operation": 61}, {"time": 11365, "train": 17, "operation": 39}, {"time": 11407, "train": 6, "operation": 61}, {"time": 11421, "train": 3, "operation": 37}, {"time": 11465, "train": 11, "operation": 69}, {"time": 11471, "train": 16, "operation": 36}, {"time": 11472, "train": 3, "operation": 38}, {"time": 11546, "train": 7, "operation": 42}, {"time": 11562, "train": 6, "operation": 63}, {"time": 11568, "train": 12, "operation": 28}, {"time": 11585, "train": 3, "operation": 40}, {"time": 11587, "train": 1, "operation": 22}, {"time": 11589, "train": 1, "operation": 23}, {"time": 11641, "train": 13, "operation": 58}, {"time": 11647, "train": 4, "operation": 49}, {"time": 11761, "train": 16, "operation": 38}, {"time": 11796, "train": 13, "operation": 60}, {"time": 11874, "train": 10, "operation": 32}, {"time": 11876, "train": 10, "operation": 34}, {"time": 11891, "train": 10, "operation": 35}, {"time": 11937, "train": 17, "operation": 40}, {"time": 11942, "train": 4, "operation": 51}, {"time": 11964, "train": 7, "operation": 44}, {"time": 11991, "train": 11, "operation": 71}, {"time": 12037, "train": 9, "operation": 63}, {"time": 12040, "train": 1, "operation": 26}, {"time": 12041, "train": 17, "operation": 42}, {"time": 12042, "train": 1, "operation": 27}, {"time": 12086, "train": 10, "operation": 37}, {"time": 12158, "train": 8, "operation": 46}, {"time": 12172, "train": 11, "operation": 72}, {"time": 12175, "train": 8, "operation": 48}, {"time": 12195, "train": 2, "operation": 60}, {"time": 12300, "train": 6, "operation": 64}, {"time": 12333, "train": 16, "operation": 39}, {"time": 12335, "train": 10, "operation": 38}, {"time": 12353, "train": 2, "operation": 61}, {"time": 12375, "train": 8, "operation": 49}, {"time": 12501, "train": 17, "operation": 44}, {"time": 12559, "train": 6, "operation": 66}, {"time": 12571, "train": 14, "operation": 18}, {"time": 12583, "train": 14, "operation": 19}, {"time": 12689, "train": 2, "operation": 62}, {"time": 12692, "train": 4, "operation": 52}, {"time": 12693, "train": 3, "operation": 41}, {"time": 12795, "train": 11, "operation": 73}, {"time": 12811, "train": 13, "operation": 61}, {"time": 12833, "train": 2, "operation": 64}, {"time": 12836, "train": 1, "operation": 28}, {"time": 12870, "train": 3, "operation": 43}, {"time": 12890, "train": 11, "operation": 75}, {"time": 12912, "train": 7, "operation": 46}, {"time": 12923, "train": 6, "operation": 67}, {"time": 13041, "train": 13, "operation": 63}, {"time": 13091, "train": 7, "operation": 47}, {"time": 13117, "train": 10, "operation": 40}, {"time": 13144, "train": 1, "operation": 30}, {"time": 13148, "train": 16, "operation": 40}, {"time": 13150, "train": 10, "operation": 41}, {"time": 13153, "train": 9, "operation": 64}, {"time": 13158, "train": 10, "operation": 43}, {"time": 13189, "train": 10, "operation": 44}, {"time": 13232, "train": 17, "operation": 45}, {"time": 13288, "train": 14, "operation": 20}, {"time": 13293, "train": 9, "operation": 66}, {"time": 13308, "train": 4, "operation": 54}, {"time": 13415, "train": 14, "operation": 22}, {"time": 13422, "train": 2, "operation": 66}, {"time": 13459, "train": 8, "operation": 50}, {"time": 13541, "train": 3, "operation": 44}, {"time": 13549, "train": 6, "operation": 69}, {"time": 13562, "train": 17, "operation": 46}, {"time": 13564, "train": 17, "operation": 47}, {"time": 13583, "train": 11, "operation": 76}, {"time": 13603, "train": 2, "operation": 67}, {"time": 13633, "train": 8, "operation": 52}, {"time": 13664, "train": 3, "operation": 46}, {"time": 13711, "train": 11, "operation": 78}, {"time": 13802, "train": 17, "operation": 50}, {"time": 13804, "train": 17, "operation": 51}, {"time": 13836, "train": 7, "operation": 49}, {"time": 13916, "train": 14, "operation": 23}, {"time": 13920, "train": 14, "operation": 24}, {"time": 13937, "train": 7, "operation": 52}, {"time": 13945, "train": 7, "operation": 53}, {"time": 14045, "train": 13, "operation": 64}, {"time": 14079, "train": 10, "operation": 45}, {"time": 14150, "train": 4, "operation": 56}, {"time": 14189, "train": 13, "operation": 66}, {"time": 14231, "train": 9, "operation": 67}, {"time": 14266, "train": 17, "operation": 52}, {"time": 14268, "train": 17, "operation": 54}, {"time": 14281, "train": 7, "operation": 54}, {"time": 14329, "train": 4, "operation": 57}, {"time": 14339, "train": 2, "operation": 68}, {"time": 14408, "train": 10, "operation": 46}, {"time": 14436, "train": 11, "operation": 79}, {"time": 14441, "train": 9, "operation": 69}, {"time": 14453, "train": 2, "operation": 70}, {"time": 14459, "train": 8, "operation": 53}, {"time": 14464, "train": 7, "operation": 62}, {"time": 14538, "train": 17, "operation": 56}, {"time": 14585, "train": 1, "operation": 32}, {"time": 14597, "train": 13, "operation": 67}, {"time": 14624, "train": 13, "operation": 68}, {"time": 14632, "train": 13, "operation": 69}, {"time": 14684, "train": 11, "operation": 81}, {"time": 14748, "train": 8, "operation": 55}, {"time": 14788, "train": 3, "operation": 48}, {"time": 14791, "train": 13, "operation": 71}, {"time": 14793, "train": 13, "operation": 72}, {"time": 14793, "train": 13, "operation": 73}, {"time": 14798, "train": 6, "operation": 70}, {"time": 14832, "train": 12, "operation": 29}, {"time": 14836, "train": 17, "operation": 57}, {"time": 14839, "train": 1, "operation": 33}, {"time": 14841, "train": 10, "operation": 48}, {"time": 14955, "train": 6, "operation": 72}, {"time": 14962, "train": 17, "operation": 59}, {"time": 14981, "train": 16, "operation": 42}, {"time": 14983, "train": 4, "operation": 59}, {"time": 15048, "train": 7, "operation": 63}, {"time": 15053, "train": 3, "operation": 49}, {"time": 15055, "train": 3, "operation": 50}, {"time": 15055, "train": 3, "operation": 51}, {"time": 15075, "train": 4, "operation": 62}, {"time": 15081, "train": 4, "operation": 63}, {"time": 15155, "train": 8, "operation": 56}, {"time": 15189, "train": 7, "operation": 65}, {"time": 15202, "train": 2, "operation": 72}, {"time": 15305, "train": 10, "operation": 49}, {"time": 15327, "train": 4, "operation": 64}, {"time": 15334, "train": 8, "operation": 58}, {"time": 15348, "train": 9, "operation": 70}, {"time": 15356, "train": 10, "operation": 50}, {"time": 15433, "train": 17, "operation": 61}, {"time": 15456, "train": 16, "operation": 43}, {"time": 15465, "train": 10, "operation": 52}, {"time": 15466, "train": 4, "operation": 72}, {"time": 15474, "train": 11, "operation": 83}, {"time": 15478, "train": 9, "operation": 72}, {"time": 15564, "train": 16, "operation": 45}, {"time": 15617, "train": 17, "operation": 62}, {"time": 15653, "train": 11, "operation": 84}, {"time": 15789, "train": 12, "operation": 30}, {"time": 15844, "train": 9, "operation": 73}, {"time": 15868, "train": 9, "operation": 74}, {"time": 15876, "train": 9, "operation": 75}, {"time": 15900, "train": 4, "operation": 73}, {"time": 15906, "train": 16, "operation": 46}, {"time": 15908, "train": 16, "operation": 47}, {"time": 15953, "train": 1, "operation": 34}, {"time": 15960, "train": 12, "operation": 32}, {"time": 15992, "train": 6, "operation": 73}, {"time": 16019, "train": 9, "operation": 77}, {"time": 16021, "train": 9, "operation": 78}, {"time": 16021, "train": 9, "operation": 79}, {"time": 16038, "train": 17, "operation": 64}, {"time": 16074, "train": 7, "operation": 66}, {"time": 16089, "train": 7, "operation": 67}, {"time": 16158, "train": 16, "operation": 50}, {"time": 16160, "train": 16, "operation": 51}, {"time": 16185, "train": 2, "operation": 73}, {"time": 16225, "train": 6, "operation": 75}, {"time": 16264, "train": 11, "operation": 86}, {"time": 16271, "train": 7, "operation": 69}, {"time": 16285, "train": 17, "operation": 65}, {"time": 16343, "train": 1, "operation": 36}, {"time": 16350, "train": 11, "operation": 89}, {"time": 16471, "train": 4, "operation": 75}, {"time": 16575, "train": 11, "operation": 90}, {"time": 16622, "train": 16, "operation": 52}, {"time": 16624, "train": 16, "operation": 54}, {"time": 16628, "train": 10, "operation": 53}, {"time": 16734, "train": 8, "operation": 59}, {"time": 16802, "train": 11, "operation": 91}, {"time": 16813, "train": 10, "operation": 55}, {"time": 16877, "train": 17, "operation": 67}, {"time": 16882, "train": 12, "operation": 33}, {"time": 16910, "train": 8, "operation": 61}, {"time": 16921, "train": 16, "operation": 56}, {"time": 16930, "train": 11, "operation": 99}, {"time": 16949, "train": 2, "operation": 74}, {"time": 17011, "train": 12, "operation": 35}, {"time": 17116, "train": 4, "operation": 76}, {"time": 17126, "train": 4, "operation": 77}, {"time": 17130, "train": 2, "operation": 76}, {"time": 17223, "train": 7, "operation": 70}, {"time": 17248, "train": 6, "operation": 76}, {"time": 17330, "train": 16, "operation": 57}, {"time": 17355, "train": 11, "operation": 100}, {"time": 17364, "train": 7, "operation": 72}, {"time": 17394, "train": 6, "operation": 78}, {"time": 17473, "train": 1, "operation": 41}, {"time": 17475, "train": 1, "operation": 43}, {"time": 17490, "train": 1, "operation": 44}, {"time": 17505, "train": 16, "operation": 59}, {"time": 17511, "train": 10, "operation": 56}, {"time": 17512, "train": 11, "operation": 102}, {"time": 17620, "train": 4, "operation": 79}, {"time": 17636, "train": 10, "operation": 58}, {"time": 17676, "train": 1, "operation": 46}, {"time": 17809, "train": 6, "operation": 79}, {"time": 17837, "train": 6, "operation": 80}, {"time": 17845, "train": 6, "operation": 81}, {"time": 17918, "train": 1, "operation": 47}, {"time": 17939, "train": 12, "operation": 37}, {"time": 17980, "train": 2, "operation": 78}, {"time": 18008, "train": 6, "operation": 83}, {"time": 18010, "train": 6, "operation": 84}, {"time": 18010, "train": 6, "operation": 85}, {"time": 18053, "train": 7, "operation": 74}, {"time": 18070, "train": 11, "operation": 103}, {"time": 18075, "train": 8, "operation": 62}, {"time": 18078, "train": 11, "operation": 104}, {"time": 18120, "train": 12, "operation": 38}, {"time": 18156, "train": 16, "operation": 60}, {"time": 18159, "train": 2, "operation": 79}, {"time": 18285, "train": 16, "operation": 62}, {"time": 18335, "train": 8, "operation": 64}, {"time": 18344, "train": 7, "operation": 75}, {"time": 18358, "train": 4, "operation": 81}, {"time": 18376, "train": 5, "operation": 1}, {"time": 18406, "train": 21, "operation": 1}, {"time": 18406, "train": 21, "operation": 2}, {"time": 18418, "train": 21, "operation": 3}, {"time": 18516, "train": 4, "operation": 82}, {"time": 18661, "train": 21, "operation": 5}, {"time": 18662, "train": 7, "operation": 76}, {"time": 18669, "train": 21, "operation": 6}, {"time": 18697, "train": 21, "operation": 7}, {"time": 18753, "train": 1, "operation": 49}, {"time": 18754, "train": 11, "operation": 106}, {"time": 18785, "train": 1, "operation": 50}, {"time": 18793, "train": 1, "operation": 52}, {"time": 18802, "train": 7, "operation": 78}, {"time": 18822, "train": 1, "operation": 53}, {"time": 18823, "train": 2, "operation": 80}, {"time": 18832, "train": 10, "operation": 60}, {"time": 18840, "train": 12, "operation": 40}, {"time": 18874, "train": 16, "operation": 63}, {"time": 18916, "train": 2, "operation": 82}, {"time": 19049, "train": 16, "operation": 65}, {"time": 19061, "train": 2, "operation": 84}, {"time": 19067, "train": 2, "operation": 85}, {"time": 19067, "train": 12, "operation": 41}, {"time": 19068, "train": 4, "operation": 84}, {"time": 19119, "train": 21, "operation": 9}, {"time": 19120, "train": 10, "operation": 61}, {"time": 19122, "train": 10, "operation": 62}, {"time": 19122, "train": 10, "operation": 63}, {"time": 19317, "train": 2, "operation": 86}, {"time": 19359, "train": 4, "operation": 85}, {"time": 19395, "train": 11, "operation": 107}, {"time": 19458, "train": 2, "operation": 94}, {"time": 19480, "train": 12, "operation": 43}, {"time": 19483, "train": 8, "operation": 65}, {"time": 19493, "train": 11, "operation": 109}, {"time": 19617, "train": 1, "operation": 54}, {"time": 19630, "train": 4, "operation": 86}, {"time": 19638, "train": 12, "operation": 44}, {"time": 19647, "train": 8, "operation": 67}, {"time": 19686, "train": 5, "operation": 2}, {"time": 19883, "train": 16, "operation": 66}, {"time": 19901, "train": 2, "operation": 95}, {"time": 19941, "train": 1, "operation": 55}, {"time": 19965, "train": 11, "operation": 111}, {"time": 19997, "train": 5, "operation": 4}, {"time": 20014, "train": 7, "operation": 79}, {"time": 20021, "train": 2, "operation": 97}, {"time": 20028, "train": 16, "operation": 68}, {"time": 20112, "train": 8, "operation": 68}, {"time": 20143, "train": 8, "operation": 69}, {"time": 20152, "train": 8, "operation": 71}, {"time": 20256, "train": 11, "operation": 112}, {"time": 20259, "train": 7, "operation": 81}, {"time": 20335, "train": 8, "operation": 72}, {"time": 20337, "train": 8, "operation": 73}, {"time": 20337, "train": 8, "operation": 74}, {"time": 20410, "train": 4, "operation": 88}, {"time": 20416, "train": 1, "operation": 57}, {"time": 20679, "train": 2, "operation": 98}, {"time": 20689, "train": 2, "operation": 99}, {"time": 20752, "train": 12, "operation": 45}, {"time": 20806, "train": 11, "operation": 113}, {"time": 20819, "train": 2, "operation": 101}, {"time": 20821, "train": 1, "operation": 58}, {"time": 20872, "train": 1, "operation": 59}, {"time": 20906, "train": 16, "operation": 70}, {"time": 20985, "train": 1, "operation": 61}, {"time": 21143, "train": 5, "operation": 5}, {"time": 21148, "train": 16, "operation": 71}, {"time": 21192, "train": 7, "operation": 83}, {"time": 21302, "train": 12, "operation": 47}, {"time": 21332, "train": 4, "operation": 89}, {"time": 21350, "train": 5, "operation": 7}, {"time": 21463, "train": 7, "operation": 84}, {"time": 21571, "train": 2, "operation": 102}, {"time": 21588, "train": 4, "operation": 91}, {"time": 21688, "train": 2, "operation": 104}, {"time": 21728, "train": 11, "operation": 115}, {"time": 22133, "train": 1, "operation": 62}, {"time": 22197, "train": 12, "operation": 48}, {"time": 22250, "train": 2, "operation": 106}, {"time": 22278, "train": 16, "operation": 73}, {"time": 22316, "train": 1, "operation": 64}, {"time": 22339, "train": 4, "operation": 93}, {"time": 22339, "train": 12, "operation": 50}, {"time": 22404, "train": 7, "operation": 85}, {"time": 22436, "train": 16, "operation": 74}, {"time": 22471, "train": 5, "operation": 8}, {"time": 22533, "train": 11, "operation": 116}, {"time": 22541, "train": 2, "operation": 107}, {"time": 22546, "train": 7, "operation": 87}, {"time": 22624, "train": 5, "operation": 10}, {"time": 22715, "train": 14, "operation": 25}, {"time": 22715, "train": 14, "operation": 26}, {"time": 22735, "train": 11, "operation": 118}, {"time": 22800, "train": 4, "operation": 94}, {"time": 22818, "train": 2, "operation": 108}, {"time": 22865, "train": 16, "operation": 76}, {"time": 22925, "train": 14, "operation": 27}, {"time": 22938, "train": 2, "operation": 110}, {"time": 22942, "train": 7, "operation": 88}, {"time": 22968, "train": 14, "operation": 28}, {"time": 22969, "train": 7, "operation": 89}, {"time": 22989, "train": 7, "operation": 90}, {"time": 22991, "train": 1, "operation": 65}, {"time": 23116, "train": 1, "operation": 67}, {"time": 23131, "train": 7, "operation": 92}, {"time": 23134, "train": 7, "operation": 93}, {"time": 23134, "train": 7, "operation": 94}, {"time": 23162, "train": 12, "operation": 51}, {"time": 23214, "train": 15, "operation": 19}, {"time": 23335, "train": 12, "operation": 53}, {"time": 23336, "train": 14, "operation": 29}, {"time": 23343, "train": 14, "operation": 32}, {"time": 23382, "train": 11, "operation": 119}, {"time": 23497, "train": 14, "operation": 33}, {"time": 23555, "train": 4, "operation": 95}, {"time": 23599, "train": 14, "operation": 34}, {"time": 23602, "train": 15, "operation": 21}, {"time": 23666, "train": 4, "operation": 97}, {"time": 23760, "train": 5, "operation": 11}, {"time": 23878, "train": 2, "operation": 111}, {"time": 23913, "train": 15, "operation": 22}, {"time": 23919, "train": 12, "operation": 54}, {"time": 23935, "train": 5, "operation": 13}, {"time": 23951, "train": 11, "operation": 121}, {"time": 23976, "train": 4, "operation": 98}, {"time": 23996, "train": 4, "operation": 99}, {"time": 23997, "train": 2, "operation": 113}, {"time": 24002, "train": 4, "operation": 100}, {"time": 24049, "train": 12, "operation": 56}, {"time": 24121, "train": 4, "operation": 102}, {"time": 24123, "train": 4, "operation": 103}, {"time": 24123, "train": 4, "operation": 104}, {"time": 24290, "train": 1, "operation": 69}, {"time": 24559, "train": 1, "operation": 70}, {"time": 24561, "train": 1, "operation": 71}, {"time": 24561, "train": 1, "operation": 72}, {"time": 24604, "train": 14, "operation": 36}, {"time": 24615, "train": 11, "operation": 122}, {"time": 24713, "train": 11, "operation": 124}, {"time": 24728, "train": 12, "operation": 57}, {"time": 24728, "train": 15, "operation": 24}, {"time": 24764, "train": 2, "operation": 114}, {"time": 24783, "train": 14, "operation": 37}, {"time": 24800, "train": 5, "operation": 14}, {"time": 24913, "train": 12, "operation": 59}, {"time": 24914, "train": 15, "operation": 25}, {"time": 24957, "train": 23, "operation": 1}, {"time": 24957, "train": 23, "operation": 2}, {"time": 24995, "train": 11, "operation": 125}, {"time": 25011, "train": 2, "operation": 116}, {"time": 25012, "train": 5, "operation": 16}, {"time": 25013, "train": 11, "operation": 126}, {"time": 25019, "train": 11, "operation": 127}, {"time": 25123, "train": 11, "operation": 129}, {"time": 25125, "train": 11, "operation": 130}, {"time": 25125, "train": 11, "operation": 131}, {"time": 25196, "train": 16, "operation": 77}, {"time": 25247, "train": 23, "operation": 4}, {"time": 25304, "train": 12, "operation": 61}, {"time": 25442, "train": 23, "operation": 5}, {"time": 25477, "train": 12, "operation": 63}, {"time": 25479, "train": 12, "operation": 64}, {"time": 25514, "train": 5, "operation": 17}, {"time": 25663, "train": 5, "operation": 19}, {"time": 25781, "train": 2, "operation": 117}, {"time": 25894, "train": 2, "operation": 119}, {"time": 25921, "train": 23, "operation": 7}, {"time": 25922, "train": 12, "operation": 65}, {"time": 25924, "train": 12, "operation": 66}, {"time": 25941, "train": 16, "operation": 79}, {"time": 26038, "train": 14, "operation": 39}, {"time": 26105, "train": 23, "operation": 8}, {"time": 26122, "train": 16, "operation": 80}, {"time": 26177, "train": 21, "operation": 10}, {"time": 26210, "train": 2, "operation": 120}, {"time": 26231, "train": 2, "operation": 121}, {"time": 26237, "train": 2, "operation": 122}, {"time": 26239, "train": 15, "operation": 26}, {"time": 26335, "train": 14, "operation": 40}, {"time": 26358, "train": 2, "operation": 124}, {"time": 26360, "train": 2, "operation": 125}, {"time": 26360, "train": 2, "operation": 126}, {"time": 26380, "train": 12, "operation": 69}, {"time": 26382, "train": 12, "operation": 70}, {"time": 26443, "train": 15, "operation": 28}, {"time": 26459, "train": 15, "operation": 29}, {"time": 26747, "train": 23, "operation": 9}, {"time": 26756, "train": 20, "operation": 1}, {"time": 26756, "train": 20, "operation": 2}, {"time": 26771, "train": 20, "operation": 3}, {"time": 26884, "train": 23, "operation": 11}, {"time": 27003, "train": 20, "operation": 5}, {"time": 27011, "train": 5, "operation": 21}, {"time": 27011, "train": 20, "operation": 6}, {"time": 27020, "train": 12, "operation": 71}, {"time": 27038, "train": 20, "operation": 7}, {"time": 27050, "train": 16, "operation": 81}, {"time": 27167, "train": 22, "operation": 1}, {"time": 27167, "train": 22, "operation": 2}, {"time": 27199, "train": 5, "operation": 22}, {"time": 27228, "train": 21, "operation": 12}, {"time": 27294, "train": 15, "operation": 30}, {"time": 27298, "train": 12, "operation": 73}, {"time": 27399, "train": 22, "operation": 3}, {"time": 27416, "train": 20, "operation": 8}, {"time": 27416, "train": 24, "operation": 1}, {"time": 27416, "train": 24, "operation": 2}, {"time": 27446, "train": 15, "operation": 32}, {"time": 27457, "train": 14, "operation": 41}, {"time": 27479, "train": 23, "operation": 12}, {"time": 27503, "train": 21, "operation": 13}, {"time": 27586, "train": 23, "operation": 14}, {"time": 27624, "train": 20, "operation": 10}, {"time": 27635, "train": 22, "operation": 5}, {"time": 27637, "train": 23, "operation": 15}, {"time": 27643, "train": 22, "operation": 6}, {"time": 27654, "train": 14, "operation": 43}, {"time": 27795, "train": 19, "operation": 1}, {"time": 27812, "train": 22, "operation": 7}, {"time": 27973, "train": 24, "operation": 3}, {"time": 28005, "train": 19, "operation": 2}, {"time": 28031, "train": 19, "operation": 3}, {"time": 28033, "train": 23, "operation": 17}, {"time": 28046, "train": 15, "operation": 33}, {"time": 28051, "train": 15, "operation": 34}, {"time": 28057, "train": 15, "operation": 35}, {"time": 28219, "train": 22, "operation": 9}, {"time": 28237, "train": 23, "operation": 18}, {"time": 28277, "train": 5, "operation": 23}, {"time": 28369, "train": 19, "operation": 5}, {"time": 28381, "train": 19, "operation": 6}, {"time": 28403, "train": 23, "operation": 19}, {"time": 28427, "train": 18, "operation": 1}, {"time": 28427, "train": 18, "operation": 2}, {"time": 28452, "train": 12, "operation": 75}, {"time": 28454, "train": 5, "operation": 25}, {"time": 28508, "train": 20, "operation": 11}, {"time": 28528, "train": 21, "operation": 14}, {"time": 28615, "train": 19, "operation": 7}, {"time": 28673, "train": 17, "operation": 68}, {"time": 28674, "train": 21, "operation": 16}, {"time": 28679, "train": 12, "operation": 76}, {"time": 28716, "train": 23, "operation": 22}, {"time": 28730, "train": 23, "operation": 26}, {"time": 28735, "train": 14, "operation": 45}, {"time": 28765, "train": 18, "operation": 3}, {"time": 28848, "train": 24, "operation": 5}, {"time": 28904, "train": 22, "operation": 10}, {"time": 28908, "train": 14, "operation": 46}, {"time": 28924, "train": 20, "operation": 13}, {"time": 28941, "train": 23, "operation": 27}, {"time": 28965, "train": 18, "operation": 5}, {"time": 29011, "train": 18, "operation": 6}, {"time": 29046, "train": 23, "operation": 29}, {"time": 29131, "train": 16, "operation": 83}, {"time": 29135, "train": 23, "operation": 30}, {"time": 29146, "train": 23, "operation": 32}, {"time": 29148, "train": 23, "operation": 34}, {"time": 29170, "train": 23, "operation": 35}, {"time": 29300, "train": 19, "operation": 9}, {"time": 29305, "train": 17, "operation": 70}, {"time": 29444, "train": 5, "operation": 26}, {"time": 29485, "train": 17, "operation": 71}, {"time": 29495, "train": 23, "operation": 36}, {"time": 29629, "train": 12, "operation": 77}, {"time": 29653, "train": 5, "operation": 28}, {"time": 29696, "train": 18, "operation": 7}, {"time": 29772, "train": 24, "operation": 6}, {"time": 29774, "train": 20, "operation": 14}, {"time": 29905, "train": 21, "operation": 18}, {"time": 29916, "train": 22, "operation": 12}, {"time": 29953, "train": 14, "operation": 48}, {"time": 29996, "train": 12, "operation": 79}, {"time": 30022, "train": 18, "operation": 8}, {"time": 30086, "train": 21, "operation": 19}, {"time": 30096, "train": 25, "operation": 1}, {"time": 30105, "train": 16, "operation": 84}, {"time": 30132, "train": 25, "operation": 2}, {"time": 30134, "train": 14, "operation": 49}, {"time": 30151, "train": 24, "operation": 8}, {"time": 30189, "train": 22, "operation": 13}, {"time": 30271, "train": 16, "operation": 86}, {"time": 30291, "train": 17, "operation": 72}, {"time": 30301, "train": 20, "operation": 16}, {"time": 30312, "train": 18, "operation": 10}, {"time": 30356, "train": 5, "operation": 29}, {"time": 30384, "train": 17, "operation": 74}, {"time": 30456, "train": 21, "operation": 20}, {"time": 30501, "train": 25, "operation": 4}, {"time": 30513, "train": 5, "operation": 31}, {"time": 30684, "train": 17, "operation": 75}, {"time": 30696, "train": 25, "operation": 5}, {"time": 30719, "train": 21, "operation": 22}, {"time": 30929, "train": 12, "operation": 84}, {"time": 30931, "train": 12, "operation": 86}, {"time": 30944, "train": 12, "operation": 87}, {"time": 30956, "train": 14, "operation": 51}, {"time": 30983, "train": 24, "operation": 9}, {"time": 31052, "train": 18, "operation": 12}, {"time": 31110, "train": 12, "operation": 89}, {"time": 31175, "train": 22, "operation": 14}, {"time": 31175, "train": 25, "operation": 7}, {"time": 31183, "train": 14, "operation": 52}, {"time": 31237, "train": 16, "operation": 87}, {"time": 31318, "train": 20, "operation": 17}, {"time": 31319, "train": 12, "operation": 90}, {"time": 31325, "train": 24, "operation": 11}, {"time": 31341, "train": 5, "operation": 32}, {"time": 31352, "train": 17, "operation": 77}, {"time": 31359, "train": 25, "operation": 8}, {"time": 31448, "train": 20, "operation": 19}, {"time": 31467, "train": 16, "operation": 89}, {"time": 31488, "train": 21, "operation": 23}, {"time": 31567, "train": 5, "operation": 34}, {"time": 31571, "train": 18, "operation": 13}, {"time": 31642, "train": 14, "operation": 54}, {"time": 31654, "train": 21, "operation": 25}, {"time": 31714, "train": 22, "operation": 16}, {"time": 31721, "train": 23, "operation": 38}, {"time": 31754, "train": 20, "operation": 20}, {"time": 31879, "train": 17, "operation": 79}, {"time": 31931, "train": 12, "operation": 92}, {"time": 31958, "train": 12, "operation": 93}, {"time": 31964, "train": 12, "operation": 95}, {"time": 31970, "train": 20, "operation": 22}, {"time": 31990, "train": 12, "operation": 96}, {"time": 32000, "train": 24, "operation": 16}, {"time": 32002, "train": 24, "operation": 17}, {"time": 32011, "train": 23, "operation": 39}, {"time": 32042, "train": 5, "operation": 36}, {"time": 32060, "train": 17, "operation": 80}, {"time": 32107, "train": 14, "operation": 55}, {"time": 32253, "train": 5, "operation": 38}, {"time": 32255, "train": 5, "operation": 39}, {"time": 32280, "train": 18, "operation": 14}, {"time": 32305, "train": 25, "operation": 10}, {"time": 32363, "train": 24, "operation": 19}, {"time": 32522, "train": 16, "operation": 91}, {"time": 32537, "train": 23, "operation": 40}, {"time": 32550, "train": 25, "operation": 11}, {"time": 32609, "train": 20, "operation": 23}, {"time": 32641, "train": 23, "operation": 42}, {"time": 32698, "train": 5, "operation": 40}, {"time": 32700, "train": 5, "operation": 41}, {"time": 32701, "train": 16, "operation": 92}, {"time": 32709, "train": 12, "operation": 97}, {"time": 32720, "train": 17, "operation": 82}, {"time": 32773, "train": 26, "operation": 1}, {"time": 32814, "train": 26, "operation": 2}, {"time": 32846, "train": 21, "operation": 27}, {"time": 32893, "train": 17, "operation": 83}, {"time": 32906, "train": 22, "operation": 17}, {"time": 32994, "train": 12, "operation": 98}, {"time": 33029, "train": 21, "operation": 28}, {"time": 33043, "train": 21, "operation": 29}, {"time": 33059, "train": 22, "operation": 19}, {"time": 33101, "train": 23, "operation": 44}, {"time": 33169, "train": 5, "operation": 44}, {"time": 33171, "train": 5, "operation": 45}, {"time": 33220, "train": 26, "operation": 3}, {"time": 33242, "train": 20, "operation": 25}, {"time": 33280, "train": 14, "operation": 57}, {"time": 33302, "train": 18, "operation": 16}, {"time": 33322, "train": 25, "operation": 12}, {"time": 33330, "train": 12, "operation": 100}, {"time": 33372, "train": 26, "operation": 5}, {"time": 33416, "train": 22, "operation": 21}, {"time": 33460, "train": 14, "operation": 58}, {"time": 33521, "train": 16, "operation": 93}, {"time": 33560, "train": 17, "operation": 84}, {"time": 33624, "train": 16, "operation": 97}, {"time": 33681, "train": 17, "operation": 86}, {"time": 33747, "train": 12, "operation": 101}, {"time": 33798, "train": 12, "operation": 103}, {"time": 33836, "train": 21, "operation": 31}, {"time": 33951, "train": 26, "operation": 7}, {"time": 33997, "train": 5, "operation": 46}, {"time": 34017, "train": 21, "operation": 32}, {"time": 34035, "train": 12, "operation": 104}, {"time": 34164, "train": 18, "operation": 17}, {"time": 34194, "train": 25, "operation": 14}, {"time": 34221, "train": 20, "operation": 26}, {"time": 34245, "train": 25, "operation": 15}, {"time": 34275, "train": 18, "operation": 19}, {"time": 34339, "train": 5, "operation": 48}, {"time": 34365, "train": 17, "operation": 88}, {"time": 34375, "train": 20, "operation": 28}, {"time": 34387, "train": 20, "operation": 29}, {"time": 34393, "train": 23, "operation": 45}, {"time": 34408, "train": 14, "operation": 59}, {"time": 34534, "train": 18, "operation": 20}, {"time": 34563, "train": 14, "operation": 61}, {"time": 34594, "train": 21, "operation": 34}, {"time": 34598, "train": 21, "operation": 36}, {"time": 34602, "train": 21, "operation": 37}, {"time": 34641, "train": 17, "operation": 89}, {"time": 34715, "train": 18, "operation": 22}, {"time": 34721, "train": 23, "operation": 46}, {"time": 34723, "train": 23, "operation": 47}, {"time": 34812, "train": 21, "operation": 39}, {"time": 34816, "train": 21, "operation": 40}, {"time": 34820, "train": 21, "operation": 41}, {"time": 34934, "train": 25, "operation": 16}, {"time": 34960, "train": 23, "operation": 50}, {"time": 34962, "train": 23, "operation": 51}, {"time": 35060, "train": 12, "operation": 105}, {"time": 35063, "train": 20, "operation": 30}, {"time": 35143, "train": 21, "operation": 42}, {"time": 35186, "train": 20, "operation": 32}, {"time": 35226, "train": 12, "operation": 107}, {"time": 35251, "train": 18, "operation": 24}, {"time": 35252, "train": 25, "operation": 18}, {"time": 35410, "train": 18, "operation": 25}, {"time": 35424, "train": 23, "operation": 52}, {"time": 35426, "train": 23, "operation": 54}, {"time": 35435, "train": 14, "operation": 63}, {"time": 35439, "train": 25, "operation": 19}, {"time": 35444, "train": 17, "operation": 91}, {"time": 35623, "train": 17, "operation": 92}, {"time": 35647, "train": 22, "operation": 22}, {"time": 35673, "train": 20, "operation": 33}, {"time": 35677, "train": 20, "operation": 34}, {"time": 35701, "train": 23, "operation": 56}, {"time": 35733, "train": 14, "operation": 64}, {"time": 35761, "train": 25, "operation": 22}, {"time": 35775, "train": 25, "operation": 26}, {"time": 35836, "train": 5, "operation": 50}, {"time": 35894, "train": 12, "operation": 108}, {"time": 35974, "train": 23, "operation": 57}, {"time": 35986, "train": 25, "operation": 28}, {"time": 36019, "train": 12, "operation": 110}, {"time": 36098, "train": 5, "operation": 51}, {"time": 36165, "train": 25, "operation": 29}, {"time": 36201, "train": 18, "operation": 26}, {"time": 36254, "train": 25, "operation": 30}, {"time": 36265, "train": 25, "operation": 32}, {"time": 36267, "train": 25, "operation": 34}, {"time": 36278, "train": 25, "operation": 35}, {"time": 36290, "train": 26, "operation": 8}, {"time": 36324, "train": 16, "operation": 102}, {"time": 36325, "train": 18, "operation": 28}, {"time": 36335, "train": 18, "operation": 29}, {"time": 36348, "train": 14, "operation": 65}, {"time": 36389, "train": 22, "operation": 24}, {"time": 36400, "train": 16, "operation": 105}, {"time": 36485, "train": 14, "operation": 67}, {"time": 36546, "train": 16, "operation": 109}, {"time": 36552, "train": 16, "operation": 113}, {"time": 36597, "train": 22, "operation": 25}, {"time": 36786, "train": 16, "operation": 118}, {"time": 36790, "train": 16, "operation": 122}, {"time": 36794, "train": 16, "operation": 123}, {"time": 36796, "train": 17, "operation": 93}, {"time": 36899, "train": 17, "operation": 97}, {"time": 36911, "train": 18, "operation": 31}, {"time": 37004, "train": 16, "operation": 125}, {"time": 37008, "train": 16, "operation": 126}, {"time": 37012, "train": 16, "operation": 127}, {"time": 37026, "train": 12, "operation": 112}, {"time": 37258, "train": 14, "operation": 69}, {"time": 37262, "train": 12, "operation": 113}, {"time": 37264, "train": 12, "operation": 114}, {"time": 37264, "train": 12, "operation": 115}, {"time": 37267, "train": 5, "operation": 52}, {"time": 37367, "train": 25, "operation": 37}, {"time": 37437, "train": 16, "operation": 128}, {"time": 37445, "train": 26, "operation": 10}, {"time": 37507, "train": 14, "operation": 70}, {"time": 37544, "train": 16, "operation": 130}, {"time": 37654, "train": 23, "operation": 59}, {"time": 37663, "train": 25, "operation": 39}, {"time": 37682, "train": 26, "operation": 11}, {"time": 37727, "train": 5, "operation": 54}, {"time": 37730, "train": 22, "operation": 26}, {"time": 37833, "train": 18, "operation": 32}, {"time": 37939, "train": 14, "operation": 72}, {"time": 38061, "train": 23, "operation": 60}, {"time": 38104, "train": 16, "operation": 131}, {"time": 38112, "train": 16, "operation": 133}, {"time": 38139, "train": 23, "operation": 62}, {"time": 38144, "train": 14, "operation": 74}, {"time": 38191, "train": 14, "operation": 75}, {"time": 38237, "train": 18, "operation": 33}, {"time": 38295, "train": 16, "operation": 134}, {"time": 38350, "train": 25, "operation": 41}, {"time": 38361, "train": 18, "operation": 41}, {"time": 38462, "train": 26, "operation": 12}, {"time": 38500, "train": 23, "operation": 63}, {"time": 38508, "train": 22, "operation": 28}, {"time": 38522, "train": 22, "operation": 29}, {"time": 38529, "train": 25, "operation": 42}, {"time": 38567, "train": 18, "operation": 42}, {"time": 38573, "train": 18, "operation": 43}, {"time": 38588, "train": 26, "operation": 14}, {"time": 38605, "train": 23, "operation": 65}, {"time": 38634, "train": 14, "operation": 76}, {"time": 38643, "train": 26, "operation": 15}, {"time": 38682, "train": 14, "operation": 77}, {"time": 38937, "train": 16, "operation": 136}, {"time": 38964, "train": 5, "operation": 59}, {"time": 38966, "train": 5, "operation": 61}, {"time": 38982, "train": 5, "operation": 62}, {"time": 38989, "train": 25, "operation": 43}, {"time": 39041, "train": 27, "operation": 1}, {"time": 39041, "train": 27, "operation": 2}, {"time": 39048, "train": 27, "operation": 3}, {"time": 39095, "train": 16, "operation": 137}, {"time": 39109, "train": 23, "operation": 66}, {"time": 39140, "train": 14, "operation": 80}, {"time": 39142, "train": 14, "operation": 81}, {"time": 39181, "train": 5, "operation": 64}, {"time": 39185, "train": 27, "operation": 5}, {"time": 39189, "train": 23, "operation": 68}, {"time": 39189, "train": 27, "operation": 6}, {"time": 39205, "train": 27, "operation": 7}, {"time": 39293, "train": 22, "operation": 30}, {"time": 39444, "train": 5, "operation": 65}, {"time": 39462, "train": 27, "operation": 8}, {"time": 39529, "train": 26, "operation": 17}, {"time": 39553, "train": 27, "operation": 10}, {"time": 39565, "train": 16, "operation": 139}, {"time": 39599, "train": 17, "operation": 102}, {"time": 39675, "train": 17, "operation": 105}, {"time": 39734, "train": 23, "operation": 69}, {"time": 39821, "train": 17, "operation": 109}, {"time": 39824, "train": 23, "operation": 71}, {"time": 39827, "train": 17, "operation": 113}, {"time": 39843, "train": 26, "operation": 18}, {"time": 39856, "train": 16, "operation": 140}, {"time": 40020, "train": 14, "operation": 83}, {"time": 40042, "train": 26, "operation": 20}, {"time": 40074, "train": 17, "operation": 117}, {"time": 40090, "train": 16, "operation": 142}, {"time": 40146, "train": 27, "operation": 11}, {"time": 40213, "train": 17, "operation": 127}, {"time": 40278, "train": 5, "operation": 67}, {"time": 40278, "train": 27, "operation": 13}, {"time": 40311, "train": 5, "operation": 68}, {"time": 40319, "train": 5, "operation": 70}, {"time": 40350, "train": 5, "operation": 71}, {"time": 40373, "train": 14, "operation": 84}, {"time": 40381, "train": 28, "operation": 1}, {"time": 40381, "train": 28, "operation": 2}, {"time": 40390, "train": 28, "operation": 4}, {"time": 40416, "train": 25, "operation": 45}, {"time": 40514, "train": 23, "operation": 72}, {"time": 40530, "train": 15, "operation": 36}, {"time": 40530, "train": 15, "operation": 37}, {"time": 40583, "train": 28, "operation": 5}, {"time": 40589, "train": 28, "operation": 6}, {"time": 40593, "train": 23, "operation": 74}, {"time": 40607, "train": 28, "operation": 7}, {"time": 40652, "train": 17, "operation": 129}, {"time": 40715, "train": 26, "operation": 23}, {"time": 40717, "train": 26, "operation": 25}, {"time": 40727, "train": 26, "operation": 26}, {"time": 40731, "train": 15, "operation": 38}, {"time": 40737, "train": 15, "operation": 39}, {"time": 40743, "train": 15, "operation": 40}, {"time": 40749, "train": 25, "operation": 46}, {"time": 40751, "train": 25, "operation": 48}, {"time": 40763, "train": 24, "operation": 21}, {"time": 40827, "train": 27, "operation": 14}, {"time": 40833, "train": 17, "operation": 130}, {"time": 40845, "train": 23, "operation": 75}, {"time": 40889, "train": 28, "operation": 8}, {"time": 40915, "train": 27, "operation": 16}, {"time": 40952, "train": 26, "operation": 27}, {"time": 40958, "train": 23, "operation": 77}, {"time": 41002, "train": 28, "operation": 10}, {"time": 41048, "train": 22, "operation": 32}, {"time": 41058, "train": 26, "operation": 29}, {"time": 41062, "train": 25, "operation": 49}, {"time": 41075, "train": 25, "operation": 50}, {"time": 41077, "train": 25, "operation": 51}, {"time": 41105, "train": 15, "operation": 41}, {"time": 41109, "train": 15, "operation": 44}, {"time": 41149, "train": 26, "operation": 31}, {"time": 41163, "train": 26, "operation": 35}, {"time": 41267, "train": 15, "operation": 45}, {"time": 41360, "train": 15, "operation": 46}, {"time": 41406, "train": 23, "operation": 78}, {"time": 41435, "train": 24, "operation": 31}, {"time": 41439, "train": 24, "operation": 32}, {"time": 41485, "train": 17, "operation": 131}, {"time": 41496, "train": 17, "operation": 132}, {"time": 41496, "train": 23, "operation": 80}, {"time": 41513, "train": 26, "operation": 37}, {"time": 41539, "train": 25, "operation": 52}, {"time": 41541, "train": 25, "operation": 54}, {"time": 41607, "train": 22, "operation": 34}, {"time": 41611, "train": 22, "operation": 37}, {"time": 41615, "train": 22, "operation": 40}, {"time": 41624, "train": 17, "operation": 134}, {"time": 41624, "train": 27, "operation": 17}, {"time": 41697, "train": 28, "operation": 12}, {"time": 41712, "train": 27, "operation": 19}, {"time": 41809, "train": 26, "operation": 39}, {"time": 41825, "train": 22, "operation": 43}, {"time": 41839, "train": 25, "operation": 56}, {"time": 41962, "train": 27, "operation": 20}, {"time": 41968, "train": 28, "operation": 13}, {"time": 41978, "train": 14, "operation": 86}, {"time": 42031, "train": 24, "operation": 35}, {"time": 42062, "train": 23, "operation": 81}, {"time": 42132, "train": 27, "operation": 21}, {"time": 42148, "train": 23, "operation": 83}, {"time": 42203, "train": 25, "operation": 58}, {"time": 42255, "train": 24, "operation": 36}, {"time": 42311, "train": 15, "operation": 48}, {"time": 42371, "train": 17, "operation": 136}, {"time": 42432, "train": 27, "operation": 22}, {"time": 42452, "train": 25, "operation": 59}, {"time": 42472, "train": 24, "operation": 38}, {"time": 42490, "train": 15, "operation": 49}, {"time": 42532, "train": 28, "operation": 14}, {"time": 42590, "train": 27, "operation": 23}, {"time": 42614, "train": 26, "operation": 40}, {"time": 42622, "train": 28, "operation": 16}, {"time": 42651, "train": 5, "operation": 72}, {"time": 42698, "train": 23, "operation": 84}, {"time": 42732, "train": 26, "operation": 42}, {"time": 42805, "train": 23, "operation": 86}, {"time": 42846, "train": 24, "operation": 39}, {"time": 42864, "train": 29, "operation": 1}, {"time": 42865, "train": 29, "operation": 2}, {"time": 42873, "train": 29, "operation": 3}, {"time": 42897, "train": 24, "operation": 40}, {"time": 42978, "train": 25, "operation": 61}, {"time": 42999, "train": 5, "operation": 73}, {"time": 43007, "train": 24, "operation": 42}, {"time": 43013, "train": 27, "operation": 24}, {"time": 43035, "train": 29, "operation": 5}, {"time": 43039, "train": 29, "operation": 6}, {"time": 43058, "train": 29, "operation": 7}, {"time": 43101, "train": 27, "operation": 26}, {"time": 43162, "train": 25, "operation": 62}, {"time": 43206, "train": 26, "operation": 43}, {"time": 43305, "train": 14, "operation": 87}, {"time": 43314, "train": 26, "operation": 45}, {"time": 43357, "train": 29, "operation": 8}, {"time": 43370, "train": 28, "operation": 17}, {"time": 43424, "train": 23, "operation": 88}, {"time": 43469, "train": 28, "operation": 19}, {"time": 43470, "train": 29, "operation": 10}, {"time": 43485, "train": 5, "operation": 75}, {"time": 43595, "train": 15, "operation": 50}, {"time": 43625, "train": 25, "operation": 64}, {"time": 43654, "train": 26, "operation": 46}, {"time": 43656, "train": 26, "operation": 48}, {"time": 43677, "train": 27, "operation": 27}, {"time": 43701, "train": 28, "operation": 20}, {"time": 43765, "train": 27, "operation": 29}, {"time": 43766, "train": 16, "operation": 143}, {"time": 43772, "train": 27, "operation": 30}, {"time": 43793, "train": 24, "operation": 43}, {"time": 43854, "train": 15, "operation": 52}, {"time": 43861, "train": 28, "operation": 22}, {"time": 43872, "train": 25, "operation": 65}, {"time": 43926, "train": 5, "operation": 76}, {"time": 43926, "train": 24, "operation": 45}, {"time": 43966, "train": 26, "operation": 49}, {"time": 43977, "train": 5, "operation": 77}, {"time": 43979, "train": 26, "operation": 50}, {"time": 43981, "train": 26, "operation": 51}, {"time": 43991, "train": 23, "operation": 89}, {"time": 44161, "train": 29, "operation": 11}, {"time": 44189, "train": 5, "operation": 79}, {"time": 44238, "train": 27, "operation": 31}, {"time": 44309, "train": 29, "operation": 13}, {"time": 44326, "train": 27, "operation": 33}, {"time": 44336, "train": 28, "operation": 23}, {"time": 44435, "train": 14, "operation": 88}, {"time": 44435, "train": 28, "operation": 25}, {"time": 44443, "train": 26, "operation": 52}, {"time": 44445, "train": 26, "operation": 54}, {"time": 44525, "train": 22, "operation": 46}, {"time": 44527, "train": 25, "operation": 66}, {"time": 44542, "train": 24, "operation": 46}, {"time": 44557, "train": 19, "operation": 10}, {"time": 44571, "train": 16, "operation": 145}, {"time": 44637, "train": 25, "operation": 68}, {"time": 44652, "train": 27, "operation": 34}, {"time": 44653, "train": 24, "operation": 48}, {"time": 44681, "train": 22, "operation": 50}, {"time": 44687, "train": 22, "operation": 53}, {"time": 44732, "train": 17, "operation": 137}, {"time": 44741, "train": 26, "operation": 56}, {"time": 44744, "train": 23, "operation": 91}, {"time": 44751, "train": 27, "operation": 42}, {"time": 44816, "train": 14, "operation": 90}, {"time": 44856, "train": 15, "operation": 53}, {"time": 44928, "train": 29, "operation": 14}, {"time": 44931, "train": 27, "operation": 43}, {"time": 44933, "train": 27, "operation": 45}, {"time": 45027, "train": 29, "operation": 16}, {"time": 45034, "train": 15, "operation": 55}, {"time": 45051, "train": 27, "operation": 46}, {"time": 45086, "train": 28, "operation": 26}, {"time": 45146, "train": 26, "operation": 57}, {"time": 45188, "train": 28, "operation": 28}, {"time": 45194, "train": 28, "operation": 29}, {"time": 45221, "train": 27, "operation": 47}, {"time": 45319, "train": 26, "operation": 59}, {"time": 45324, "train": 16, "operation": 146}, {"time": 45334, "train": 25, "operation": 70}, {"time": 45378, "train": 24, "operation": 49}, {"time": 45401, "train": 27, "operation": 48}, {"time": 45427, "train": 27, "operation": 49}, {"time": 45466, "train": 5, "operation": 80}, {"time": 45493, "train": 17, "operation": 139}, {"time": 45514, "train": 25, "operation": 71}, {"time": 45559, "train": 24, "operation": 51}, {"time": 45561, "train": 24, "operation": 52}, {"time": 45561, "train": 24, "operation": 53}, {"time": 45665, "train": 5, "operation": 82}, {"time": 45721, "train": 28, "operation": 30}, {"time": 45820, "train": 28, "operation": 32}, {"time": 45831, "train": 29, "operation": 17}, {"time": 45930, "train": 29, "operation": 19}, {"time": 45964, "train": 26, "operation": 60}, {"time": 45965, "train": 14, "operation": 95}, {"time": 45967, "train": 14, "operation": 97}, {"time": 45969, "train": 27, "operation": 50}, {"time": 45973, "train": 16, "operation": 148}, {"time": 45982, "train": 14, "operation": 98}, {"time": 45995, "train": 15, "operation": 56}, {"time": 46054, "train": 27, "operation": 52}, {"time": 46092, "train": 26, "operation": 62}, {"time": 46130, "train": 15, "operation": 58}, {"time": 46162, "train": 29, "operation": 20}, {"time": 46171, "train": 14, "operation": 100}, {"time": 46189, "train": 28, "operation": 33}, {"time": 46322, "train": 29, "operation": 22}, {"time": 46341, "train": 19, "operation": 11}, {"time": 46381, "train": 5, "operation": 83}, {"time": 46402, "train": 25, "operation": 73}, {"time": 46415, "train": 14, "operation": 101}, {"time": 46471, "train": 28, "operation": 35}, {"time": 46479, "train": 18, "operation": 44}, {"time": 46479, "train": 18, "operation": 45}, {"time": 46520, "train": 5, "operation": 85}, {"time": 46558, "train": 17, "operation": 140}, {"time": 46560, "train": 25, "operation": 74}, {"time": 46675, "train": 26, "operation": 64}, {"time": 46735, "train": 18, "operation": 46}, {"time": 46737, "train": 16, "operation": 149}, {"time": 46758, "train": 19, "operation": 13}, {"time": 46779, "train": 27, "operation": 53}, {"time": 46797, "train": 29, "operation": 24}, {"time": 46833, "train": 17, "operation": 141}, {"time": 46895, "train": 25, "operation": 76}, {"time": 46915, "train": 27, "operation": 55}, {"time": 46922, "train": 26, "operation": 65}, {"time": 46952, "train": 17, "operation": 143}, {"time": 46955, "train": 29, "operation": 25}, {"time": 47086, "train": 15, "operation": 60}, {"time": 47254, "train": 14, "operation": 103}, {"time": 47286, "train": 14, "operation": 104}, {"time": 47294, "train": 14, "operation": 106}, {"time": 47308, "train": 15, "operation": 61}, {"time": 47325, "train": 14, "operation": 107}, {"time": 47371, "train": 28, "operation": 38}, {"time": 47402, "train": 16, "operation": 150}, {"time": 47471, "train": 28, "operation": 41}, {"time": 47500, "train": 16, "operation": 152}, {"time": 47502, "train": 27, "operation": 56}, {"time": 47546, "train": 29, "operation": 26}, {"time": 47606, "train": 27, "operation": 58}, {"time": 47647, "train": 29, "operation": 28}, {"time": 47654, "train": 29, "operation": 29}, {"time": 47674, "train": 18, "operation": 47}, {"time": 47681, "train": 28, "operation": 43}, {"time": 47683, "train": 28, "operation": 55}, {"time": 47747, "train": 26, "operation": 66}, {"time": 47782, "train": 16, "operation": 153}, {"time": 47795, "train": 28, "operation": 56}, {"time": 47800, "train": 16, "operation": 154}, {"time": 47806, "train": 16, "operation": 155}, {"time": 47821, "train": 18, "operation": 49}, {"time": 47844, "train": 5, "operation": 87}, {"time": 47885, "train": 17, "operation": 145}, {"time": 47890, "train": 26, "operation": 68}, {"time": 47910, "train": 16, "operation": 157}, {"time": 47912, "train": 16, "operation": 158}, {"time": 47912, "train": 16, "operation": 159}, {"time": 47988, "train": 15, "operation": 62}, {"time": 48070, "train": 28, "operation": 57}, {"time": 48135, "train": 5, "operation": 88}, {"time": 48137, "train": 5, "operation": 89}, {"time": 48137, "train": 5, "operation": 90}, {"time": 48143, "train": 14, "operation": 108}, {"time": 48143, "train": 27, "operation": 59}, {"time": 48174, "train": 15, "operation": 64}, {"time": 48181, "train": 29, "operation": 30}, {"time": 48227, "train": 27, "operation": 61}, {"time": 48280, "train": 29, "operation": 32}, {"time": 48467, "train": 14, "operation": 109}, {"time": 48568, "train": 19, "operation": 14}, {"time": 48648, "train": 29, "operation": 33}, {"time": 48679, "train": 28, "operation": 58}, {"time": 48760, "train": 26, "operation": 70}, {"time": 48770, "train": 19, "operation": 16}, {"time": 48792, "train": 27, "operation": 62}, {"time": 48888, "train": 18, "operation": 50}, {"time": 48932, "train": 29, "operation": 35}, {"time": 48942, "train": 14, "operation": 111}, {"time": 48964, "train": 17, "operation": 146}, {"time": 49044, "train": 27, "operation": 63}, {"time": 49075, "train": 23, "operation": 92}, {"time": 49218, "train": 18, "operation": 52}, {"time": 49284, "train": 27, "operation": 64}, {"time": 49284, "train": 28, "operation": 60}, {"time": 49317, "train": 27, "operation": 65}, {"time": 49358, "train": 14, "operation": 112}, {"time": 49409, "train": 14, "operation": 113}, {"time": 49521, "train": 14, "operation": 115}, {"time": 49524, "train": 15, "operation": 66}, {"time": 49612, "train": 23, "operation": 93}, {"time": 49715, "train": 23, "operation": 97}, {"time": 49724, "train": 17, "operation": 147}, {"time": 49788, "train": 27, "operation": 66}, {"time": 49832, "train": 29, "operation": 38}, {"time": 49900, "train": 17, "operation": 149}, {"time": 49920, "train": 27, "operation": 68}, {"time": 49934, "train": 29, "operation": 41}, {"time": 50019, "train": 28, "operation": 61}, {"time": 50084, "train": 18, "operation": 54}, {"time": 50144, "train": 27, "operation": 69}, {"time": 50145, "train": 29, "operation": 43}, {"time": 50147, "train": 29, "operation": 54}, {"time": 50184, "train": 25, "operation": 77}, {"time": 50221, "train": 27, "operation": 71}, {"time": 50335, "train": 18, "operation": 55}, {"time": 50386, "train": 29, "operation": 57}, {"time": 50480, "train": 28, "operation": 63}, {"time": 50664, "train": 17, "operation": 150}, {"time": 50665, "train": 14, "operation": 116}, {"time": 50747, "train": 19, "operation": 18}, {"time": 50777, "train": 17, "operation": 152}, {"time": 50846, "train": 14, "operation": 118}, {"time": 50893, "train": 27, "operation": 72}, {"time": 50915, "train": 23, "operation": 102}, {"time": 50981, "train": 27, "operation": 74}, {"time": 50991, "train": 23, "operation": 105}, {"time": 51002, "train": 19, "operation": 19}, {"time": 51027, "train": 29, "operation": 58}, {"time": 51086, "train": 28, "operation": 64}, {"time": 51091, "train": 17, "operation": 153}, {"time": 51111, "train": 17, "operation": 154}, {"time": 51117, "train": 17, "operation": 155}, {"time": 51125, "train": 29, "operation": 60}, {"time": 51137, "train": 23, "operation": 109}, {"time": 51143, "train": 23, "operation": 113}, {"time": 51163, "train": 18, "operation": 56}, {"time": 51237, "train": 17, "operation": 157}, {"time": 51239, "train": 17, "operation": 158}, {"time": 51239, "train": 17, "operation": 159}, {"time": 51289, "train": 15, "operation": 67}, {"time": 51368, "train": 23, "operation": 117}, {"time": 51373, "train": 18, "operation": 58}, {"time": 51497, "train": 23, "operation": 127}, {"time": 51513, "train": 27, "operation": 75}, {"time": 51524, "train": 14, "operation": 119}, {"time": 51559, "train": 28, "operation": 66}, {"time": 51591, "train": 27, "operation": 77}, {"time": 51606, "train": 19, "operation": 20}, {"time": 51648, "train": 14, "operation": 121}, {"time": 51764, "train": 22, "operation": 57}, {"time": 51841, "train": 23, "operation": 128}, {"time": 51931, "train": 23, "operation": 130}, {"time": 51934, "train": 29, "operation": 62}, {"time": 51949, "train": 25, "operation": 79}, {"time": 52054, "train": 19, "operation": 22}, {"time": 52082, "train": 27, "operation": 78}, {"time": 52109, "train": 28, "operation": 67}, {"time": 52116, "train": 22, "operation": 61}, {"time": 52122, "train": 22, "operation": 65}, {"time": 52186, "train": 27, "operation": 80}, {"time": 52198, "train": 18, "operation": 59}, {"time": 52210, "train": 29, "operation": 63}, {"time": 52299, "train": 22, "operation": 66}, {"time": 52340, "train": 15, "operation": 68}, {"time": 52409, "train": 22, "operation": 67}, {"time": 52410, "train": 18, "operation": 61}, {"time": 52419, "train": 23, "operation": 131}, {"time": 52427, "train": 23, "operation": 133}, {"time": 52488, "train": 15, "operation": 70}, {"time": 52538, "train": 27, "operation": 81}, {"time": 52594, "train": 28, "operation": 69}, {"time": 52610, "train": 23, "operation": 134}, {"time": 52615, "train": 27, "operation": 83}, {"time": 52736, "train": 26, "operation": 71}, {"time": 52820, "train": 14, "operation": 123}, {"time": 52829, "train": 29, "operation": 64}, {"time": 52936, "train": 29, "operation": 66}, {"time": 53012, "train": 27, "operation": 84}, {"time": 53057, "train": 18, "operation": 62}, {"time": 53094, "train": 14, "operation": 124}, {"time": 53116, "train": 27, "operation": 86}, {"time": 53160, "train": 28, "operation": 70}, {"time": 53203, "train": 23, "operation": 136}, {"time": 53327, "train": 19, "operation": 23}, {"time": 53335, "train": 22, "operation": 69}, {"time": 53336, "train": 15, "operation": 71}, {"time": 53343, "train": 27, "operation": 87}, {"time": 53453, "train": 28, "operation": 72}, {"time": 53471, "train": 15, "operation": 73}, {"time": 53486, "train": 29, "operation": 67}, {"time": 53515, "train": 22, "operation": 70}, {"time": 53599, "train": 27, "operation": 89}, {"time": 53613, "train": 27, "operation": 90}, {"time": 53615, "train": 27, "operation": 91}, {"time": 53624, "train": 19, "operation": 25}, {"time": 53637, "train": 29, "operation": 69}, {"time": 53723, "train": 23, "operation": 137}, {"time": 53758, "train": 14, "operation": 125}, {"time": 53758, "train": 14, "operation": 126}, {"time": 53854, "train": 26, "operation": 73}, {"time": 53901, "train": 28, "operation": 74}, {"time": 54056, "train": 27, "operation": 92}, {"time": 54058, "train": 27, "operation": 93}, {"time": 54128, "train": 28, "operation": 75}, {"time": 54155, "train": 23, "operation": 138}, {"time": 54203, "train": 29, "operation": 70}, {"time": 54252, "train": 15, "operation": 74}, {"time": 54284, "train": 27, "operation": 96}, {"time": 54286, "train": 27, "operation": 97}, {"time": 54300, "train": 23, "operation": 140}, {"time": 54302, "train": 29, "operation": 72}, {"time": 54380, "train": 28, "operation": 76}, {"time": 54404, "train": 21, "operation": 43}, {"time": 54404, "train": 21, "operation": 44}, {"time": 54415, "train": 15, "operation": 76}, {"time": 54459, "train": 28, "operation": 78}, {"time": 54511, "train": 23, "operation": 141}, {"time": 54578, "train": 27, "operation": 98}, {"time": 54599, "train": 25, "operation": 80}, {"time": 54601, "train": 23, "operation": 143}, {"time": 54663, "train": 27, "operation": 100}, {"time": 54679, "train": 22, "operation": 72}, {"time": 54709, "train": 21, "operation": 45}, {"time": 54776, "train": 18, "operation": 64}, {"time": 54960, "train": 22, "operation": 73}, {"time": 54967, "train": 15, "operation": 77}, {"time": 55037, "train": 27, "operation": 101}, {"time": 55067, "train": 21, "operation": 46}, {"time": 55090, "train": 15, "operation": 79}, {"time": 55124, "train": 27, "operation": 103}, {"time": 55145, "train": 18, "operation": 65}, {"time": 55149, "train": 28, "operation": 79}, {"time": 55172, "train": 29, "operation": 73}, {"time": 55239, "train": 28, "operation": 81}, {"time": 55332, "train": 25, "operation": 81}, {"time": 55344, "train": 23, "operation": 144}, {"time": 55435, "train": 23, "operation": 146}, {"time": 55444, "train": 25, "operation": 83}, {"time": 55532, "train": 27, "operation": 104}, {"time": 55541, "train": 29, "operation": 75}, {"time": 55545, "train": 18, "operation": 67}, {"time": 55733, "train": 15, "operation": 80}, {"time": 55784, "train": 27, "operation": 107}, {"time": 55784, "train": 28, "operation": 82}, {"time": 55796, "train": 27, "operation": 108}, {"time": 55864, "train": 28, "operation": 84}, {"time": 55908, "train": 15, "operation": 82}, {"time": 55941, "train": 29, "operation": 76}, {"time": 55950, "train": 19, "operation": 27}, {"time": 55987, "train": 22, "operation": 74}, {"time": 56007, "train": 23, "operation": 147}, {"time": 56078, "train": 27, "operation": 109}, {"time": 56089, "train": 27, "operation": 114}, {"time": 56142, "train": 23, "operation": 149}, {"time": 56163, "train": 27, "operation": 115}, {"time": 56203, "train": 25, "operation": 85}, {"time": 56250, "train": 27, "operation": 117}, {"time": 56281, "train": 15, "operation": 83}, {"time": 56286, "train": 19, "operation": 28}, {"time": 56313, "train": 19, "operation": 29}, {"time": 56337, "train": 26, "operation": 74}, {"time": 56366, "train": 21, "operation": 48}, {"time": 56368, "train": 28, "operation": 86}, {"time": 56419, "train": 25, "operation": 86}, {"time": 56431, "train": 27, "operation": 118}, {"time": 56443, "train": 27, "operation": 123}, {"time": 56543, "train": 18, "operation": 68}, {"time": 56546, "train": 21, "operation": 49}, {"time": 56569, "train": 15, "operation": 85}, {"time": 56583, "train": 15, "operation": 86}, {"time": 56585, "train": 15, "operation": 87}, {"time": 56599, "train": 22, "operation": 76}, {"time": 56615, "train": 28, "operation": 87}, {"time": 56720, "train": 27, "operation": 124}, {"time": 56762, "train": 26, "operation": 75}, {"time": 56779, "train": 23, "operation": 150}, {"time": 56871, "train": 23, "operation": 152}, {"time": 56885, "train": 27, "operation": 125}, {"time": 56939, "train": 29, "operation": 78}, {"time": 56940, "train": 26, "operation": 77}, {"time": 56976, "train": 28, "operation": 89}, {"time": 56992, "train": 27, "operation": 127}, {"time": 57028, "train": 15, "operation": 88}, {"time": 57030, "train": 15, "operation": 89}, {"time": 57153, "train": 23, "operation": 153}, {"time": 57160, "train": 28, "operation": 90}, {"time": 57170, "train": 23, "operation": 154}, {"time": 57174, "train": 23, "operation": 155}, {"time": 57176, "train": 25, "operation": 87}, {"time": 57271, "train": 27, "operation": 128}, {"time": 57272, "train": 23, "operation": 157}, {"time": 57274, "train": 23, "operation": 158}, {"time": 57274, "train": 23, "operation": 159}, {"time": 57313, "train": 27, "operation": 129}, {"time": 57402, "train": 27, "operation": 131}, {"time": 57475, "train": 15, "operation": 92}, {"time": 57477, "train": 15, "operation": 93}, {"time": 57505, "train": 19, "operation": 31}, {"time": 57567, "train": 28, "operation": 91}, {"time": 57595, "train": 22, "operation": 77}, {"time": 57629, "train": 29, "operation": 80}, {"time": 57674, "train": 28, "operation": 93}, {"time": 57677, "train": 26, "operation": 79}, {"time": 57718, "train": 19, "operation": 32}, {"time": 57734, "train": 22, "operation": 79}, {"time": 57809, "train": 29, "operation": 81}, {"time": 57885, "train": 21, "operation": 51}, {"time": 57904, "train": 27, "operation": 132}, {"time": 57904, "train": 28, "operation": 95}, {"time": 57993, "train": 27, "operation": 134}, {"time": 58046, "train": 28, "operation": 97}, {"time": 58048, "train": 28, "operation": 98}, {"time": 58133, "train": 15, "operation": 95}, {"time": 58198, "train": 21, "operation": 52}, {"time": 58281, "train": 25, "operation": 89}, {"time": 58354, "train": 29, "operation": 82}, {"time": 58426, "train": 15, "operation": 96}, {"time": 58434, "train": 29, "operation": 84}, {"time": 58491, "train": 28, "operation": 99}, {"time": 58493, "train": 28, "operation": 100}, {"time": 58528, "train": 27, "operation": 135}, {"time": 58621, "train": 27, "operation": 137}, {"time": 58641, "train": 19, "operation": 33}, {"time": 58647, "train": 19, "operation": 34}, {"time": 58653, "train": 19, "operation": 35}, {"time": 58744, "train": 22, "operation": 80}, {"time": 58750, "train": 18, "operation": 70}, {"time": 58854, "train": 28, "operation": 103}, {"time": 58856, "train": 28, "operation": 104}, {"time": 58889, "train": 19, "operation": 36}, {"time": 58889, "train": 19, "operation": 37}, {"time": 58903, "train": 22, "operation": 82}, {"time": 58938, "train": 29, "operation": 85}, {"time": 59026, "train": 27, "operation": 138}, {"time": 59043, "train": 29, "operation": 87}, {"time": 59053, "train": 19, "operation": 38}, {"time": 59059, "train": 19, "operation": 39}, {"time": 59065, "train": 19, "operation": 40}, {"time": 59131, "train": 25, "operation": 91}, {"time": 59140, "train": 26, "operation": 80}, {"time": 59195, "train": 28, "operation": 105}, {"time": 59238, "train": 27, "operation": 139}, {"time": 59238, "train": 27, "operation": 140}, {"time": 59372, "train": 21, "operation": 54}, {"time": 59404, "train": 29, "operation": 88}, {"time": 59428, "train": 19, "operation": 41}, {"time": 59432, "train": 19, "operation": 44}, {"time": 59482, "train": 29, "operation": 90}, {"time": 59554, "train": 18, "operation": 71}, {"time": 59568, "train": 19, "operation": 45}, {"time": 59595, "train": 21, "operation": 55}, {"time": 59620, "train": 15, "operation": 97}, {"time": 59661, "train": 19, "operation": 46}, {"time": 59679, "train": 22, "operation": 83}, {"time": 59680, "train": 18, "operation": 73}, {"time": 59871, "train": 22, "operation": 85}, {"time": 59889, "train": 29, "operation": 91}, {"time": 59911, "train": 15, "operation": 99}, {"time": 59996, "train": 29, "operation": 93}, {"time": 60016, "train": 28, "operation": 107}, {"time": 60058, "train": 26, "operation": 82}, {"time": 60226, "train": 29, "operation": 94}, {"time": 60319, "train": 22, "operation": 86}, {"time": 60422, "train": 18, "operation": 74}, {"time": 60454, "train": 22, "operation": 88}, {"time": 60454, "train": 29, "operation": 96}, {"time": 60468, "train": 29, "operation": 97}, {"time": 60470, "train": 29, "operation": 98}, {"time": 60483, "train": 28, "operation": 108}, {"time": 60533, "train": 19, "operation": 47}, {"time": 60577, "train": 18, "operation": 76}, {"time": 60675, "train": 19, "operation": 49}, {"time": 60726, "train": 21, "operation": 56}, {"time": 60875, "train": 15, "operation": 100}, {"time": 60885, "train": 21, "operation": 58}, {"time": 60913, "train": 29, "operation": 99}, {"time": 60915, "train": 29, "operation": 100}, {"time": 60929, "train": 25, "operation": 92}, {"time": 61102, "train": 18, "operation": 78}, {"time": 61122, "train": 26, "operation": 83}, {"time": 61223, "train": 15, "operation": 102}, {"time": 61266, "train": 29, "operation": 103}, {"time": 61268, "train": 29, "operation": 104}, {"time": 61271, "train": 28, "operation": 110}, {"time": 61287, "train": 18, "operation": 79}, {"time": 61587, "train": 25, "operation": 94}, {"time": 61607, "train": 29, "operation": 105}, {"time": 61659, "train": 22, "operation": 89}, {"time": 61718, "train": 29, "operation": 107}, {"time": 61720, "train": 19, "operation": 50}, {"time": 61760, "train": 28, "operation": 111}, {"time": 61831, "train": 22, "operation": 91}, {"time": 61833, "train": 25, "operation": 99}, {"time": 61837, "train": 25, "operation": 104}, {"time": 61895, "train": 18, "operation": 80}, {"time": 61961, "train": 19, "operation": 52}, {"time": 62041, "train": 21, "operation": 60}, {"time": 62050, "train": 28, "operation": 114}, {"time": 62060, "train": 18, "operation": 82}, {"time": 62061, "train": 28, "operation": 115}, {"time": 62084, "train": 25, "operation": 107}, {"time": 62084, "train": 26, "operation": 85}, {"time": 62148, "train": 15, "operation": 107}, {"time": 62150, "train": 15, "operation": 109}, {"time": 62187, "train": 29, "operation": 108}, {"time": 62222, "train": 21, "operation": 61}, {"time": 62264, "train": 25, "operation": 110}, {"time": 62295, "train": 29, "operation": 110}, {"time": 62397, "train": 28, "operation": 116}, {"time": 62411, "train": 18, "operation": 84}, {"time": 62411, "train": 28, "operation": 121}, {"time": 62500, "train": 28, "operation": 122}, {"time": 62568, "train": 18, "operation": 86}, {"time": 62570, "train": 18, "operation": 87}, {"time": 62605, "train": 28, "operation": 124}, {"time": 62785, "train": 29, "operation": 111}, {"time": 62796, "train": 22, "operation": 92}, {"time": 62820, "train": 28, "operation": 125}, {"time": 62836, "train": 28, "operation": 130}, {"time": 62888, "train": 19, "operation": 53}, {"time": 62896, "train": 15, "operation": 110}, {"time": 62950, "train": 22, "operation": 94}, {"time": 63012, "train": 18, "operation": 88}, {"time": 63014, "train": 18, "operation": 89}, {"time": 63052, "train": 19, "operation": 55}, {"time": 63076, "train": 29, "operation": 113}, {"time": 63107, "train": 21, "operation": 63}, {"time": 63118, "train": 15, "operation": 112}, {"time": 63155, "train": 28, "operation": 131}, {"time": 63284, "train": 26, "operation": 86}, {"time": 63327, "train": 15, "operation": 113}, {"time": 63334, "train": 21, "operation": 64}, {"time": 63339, "train": 28, "operation": 132}, {"time": 63428, "train": 29, "operation": 118}, {"time": 63430, "train": 29, "operation": 119}, {"time": 63463, "train": 28, "operation": 134}, {"time": 63481, "train": 18, "operation": 92}, {"time": 63483, "train": 18, "operation": 93}, {"time": 63798, "train": 28, "operation": 135}, {"time": 63837, "train": 21, "operation": 66}, {"time": 63837, "train": 22, "operation": 95}, {"time": 63849, "train": 28, "operation": 136}, {"time": 63855, "train": 29, "operation": 127}, {"time": 63857, "train": 29, "operation": 128}, {"time": 63942, "train": 19, "operation": 56}, {"time": 63956, "train": 28, "operation": 138}, {"time": 63984, "train": 15, "operation": 114}, {"time": 63995, "train": 21, "operation": 67}, {"time": 64023, "train": 22, "operation": 97}, {"time": 64052, "train": 15, "operation": 119}, {"time": 64054, "train": 18, "operation": 95}, {"time": 64066, "train": 19, "operation": 58}, {"time": 64187, "train": 29, "operation": 131}, {"time": 64240, "train": 26, "operation": 87}, {"time": 64292, "train": 20, "operation": 35}, {"time": 64292, "train": 20, "operation": 36}, {"time": 64305, "train": 18, "operation": 96}, {"time": 64371, "train": 29, "operation": 132}, {"time": 64468, "train": 26, "operation": 89}, {"time": 64476, "train": 20, "operation": 37}, {"time": 64483, "train": 20, "operation": 38}, {"time": 64497, "train": 29, "operation": 134}, {"time": 64559, "train": 28, "operation": 139}, {"time": 64653, "train": 22, "operation": 98}, {"time": 64667, "train": 28, "operation": 141}, {"time": 64767, "train": 15, "operation": 120}, {"time": 64794, "train": 22, "operation": 100}, {"time": 64832, "train": 29, "operation": 135}, {"time": 64846, "train": 20, "operation": 39}, {"time": 64850, "train": 20, "operation": 41}, {"time": 64883, "train": 29, "operation": 136}, {"time": 64952, "train": 19, "operation": 59}, {"time": 64964, "train": 25, "operation": 117}, {"time": 64990, "train": 29, "operation": 138}, {"time": 65050, "train": 15, "operation": 122}, {"time": 65092, "train": 25, "operation": 127}, {"time": 65094, "train": 19, "operation": 61}, {"time": 65256, "train": 28, "operation": 142}, {"time": 65322, "train": 18, "operation": 97}, {"time": 65364, "train": 28, "operation": 144}, {"time": 65368, "train": 21, "operation": 68}, {"time": 65445, "train": 15, "operation": 123}, {"time": 65449, "train": 25, "operation": 128}, {"time": 65512, "train": 26, "operation": 91}, {"time": 65528, "train": 22, "operation": 101}, {"time": 65543, "train": 25, "operation": 130}, {"time": 65565, "train": 21, "operation": 70}, {"time": 65595, "train": 18, "operation": 99}, {"time": 65595, "train": 29, "operation": 139}, {"time": 65691, "train": 26, "operation": 92}, {"time": 65703, "train": 29, "operation": 141}, {"time": 65727, "train": 22, "operation": 103}, {"time": 65787, "train": 19, "operation": 62}, {"time": 65846, "train": 28, "operation": 145}, {"time": 65848, "train": 15, "operation": 124}, {"time": 65899, "train": 15, "operation": 125}, {"time": 65958, "train": 19, "operation": 64}, {"time": 65960, "train": 28, "operation": 147}, {"time": 66011, "train": 15, "operation": 127}, {"time": 66043, "train": 25, "operation": 131}, {"time": 66051, "train": 25, "operation": 132}, {"time": 66148, "train": 22, "operation": 105}, {"time": 66150, "train": 25, "operation": 134}, {"time": 66287, "train": 28, "operation": 148}, {"time": 66287, "train": 28, "operation": 149}, {"time": 66292, "train": 29, "operation": 142}, {"time": 66333, "train": 22, "operation": 107}, {"time": 66335, "train": 22, "operation": 108}, {"time": 66355, "train": 19, "operation": 65}, {"time": 66400, "train": 29, "operation": 144}, {"time": 66470, "train": 18, "operation": 100}, {"time": 66475, "train": 19, "operation": 67}, {"time": 66503, "train": 26, "operation": 93}, {"time": 66606, "train": 26, "operation": 97}, {"time": 66669, "train": 21, "operation": 72}, {"time": 66752, "train": 25, "operation": 135}, {"time": 66778, "train": 22, "operation": 109}, {"time": 66780, "train": 22, "operation": 110}, {"time": 66795, "train": 18, "operation": 102}, {"time": 66845, "train": 25, "operation": 137}, {"time": 66857, "train": 21, "operation": 73}, {"time": 66884, "train": 29, "operation": 145}, {"time": 66899, "train": 20, "operation": 44}, {"time": 66998, "train": 29, "operation": 147}, {"time": 67010, "train": 15, "operation": 128}, {"time": 67174, "train": 15, "operation": 130}, {"time": 67242, "train": 22, "operation": 113}, {"time": 67244, "train": 22, "operation": 114}, {"time": 67279, "train": 25, "operation": 138}, {"time": 67325, "train": 29, "operation": 148}, {"time": 67325, "train": 29, "operation": 149}, {"time": 67426, "train": 25, "operation": 140}, {"time": 67545, "train": 19, "operation": 68}, {"time": 67597, "train": 18, "operation": 107}, {"time": 67599, "train": 18, "operation": 108}, {"time": 67637, "train": 25, "operation": 141}, {"time": 67696, "train": 19, "operation": 70}, {"time": 67727, "train": 25, "operation": 143}, {"time": 67757, "train": 20, "operation": 45}, {"time": 67829, "train": 15, "operation": 131}, {"time": 67860, "train": 21, "operation": 74}, {"time": 67895, "train": 20, "operation": 47}, {"time": 67920, "train": 22, "operation": 115}, {"time": 67949, "train": 15, "operation": 133}, {"time": 68072, "train": 21, "operation": 76}, {"time": 68215, "train": 22, "operation": 117}, {"time": 68481, "train": 25, "operation": 144}, {"time": 68514, "train": 18, "operation": 116}, {"time": 68520, "train": 18, "operation": 117}, {"time": 68560, "train": 19, "operation": 71}, {"time": 68576, "train": 25, "operation": 146}, {"time": 68698, "train": 19, "operation": 73}, {"time": 68791, "train": 21, "operation": 78}, {"time": 68908, "train": 20, "operation": 48}, {"time": 68931, "train": 15, "operation": 134}, {"time": 68976, "train": 21, "operation": 79}, {"time": 69140, "train": 20, "operation": 50}, {"time": 69171, "train": 25, "operation": 147}, {"time": 69173, "train": 15, "operation": 136}, {"time": 69236, "train": 18, "operation": 120}, {"time": 69306, "train": 26, "operation": 102}, {"time": 69309, "train": 25, "operation": 149}, {"time": 69385, "train": 26, "operation": 105}, {"time": 69436, "train": 22, "operation": 119}, {"time": 69493, "train": 19, "operation": 74}, {"time": 69495, "train": 18, "operation": 121}, {"time": 69533, "train": 26, "operation": 109}, {"time": 69539, "train": 26, "operation": 113}, {"time": 69659, "train": 19, "operation": 76}, {"time": 69671, "train": 22, "operation": 120}, {"time": 69744, "train": 15, "operation": 137}, {"time": 69744, "train": 15, "operation": 138}, {"time": 69764, "train": 18, "operation": 123}, {"time": 69790, "train": 26, "operation": 117}, {"time": 69795, "train": 21, "operation": 81}, {"time": 69929, "train": 26, "operation": 127}, {"time": 69949, "train": 25, "operation": 150}, {"time": 70039, "train": 20, "operation": 51}, {"time": 70044, "train": 25, "operation": 152}, {"time": 70182, "train": 18, "operation": 124}, {"time": 70198, "train": 20, "operation": 53}, {"time": 70220, "train": 19, "operation": 77}, {"time": 70233, "train": 18, "operation": 125}, {"time": 70326, "train": 25, "operation": 153}, {"time": 70341, "train": 18, "operation": 127}, {"time": 70344, "train": 25, "operation": 154}, {"time": 70345, "train": 19, "operation": 79}, {"time": 70348, "train": 25, "operation": 155}, {"time": 70362, "train": 26, "operation": 128}, {"time": 70448, "train": 25, "operation": 157}, {"time": 70450, "train": 25, "operation": 158}, {"time": 70450, "train": 25, "operation": 159}, {"time": 70478, "train": 26, "operation": 130}, {"time": 70669, "train": 22, "operation": 121}, {"time": 71000, "train": 19, "operation": 80}, {"time": 71060, "train": 20, "operation": 54}, {"time": 71069, "train": 22, "operation": 123}, {"time": 71113, "train": 26, "operation": 131}, {"time": 71123, "train": 26, "operation": 132}, {"time": 71178, "train": 19, "operation": 82}, {"time": 71181, "train": 20, "operation": 56}, {"time": 71246, "train": 18, "operation": 129}, {"time": 71248, "train": 26, "operation": 134}, {"time": 71435, "train": 18, "operation": 130}, {"time": 71558, "train": 19, "operation": 84}, {"time": 71727, "train": 19, "operation": 86}, {"time": 71729, "train": 19, "operation": 87}, {"time": 71954, "train": 21, "operation": 82}, {"time": 71973, "train": 26, "operation": 135}, {"time": 72040, "train": 20, "operation": 57}, {"time": 72079, "train": 22, "operation": 128}, {"time": 72081, "train": 18, "operation": 132}, {"time": 72081, "train": 22, "operation": 130}, {"time": 72084, "train": 26, "operation": 137}, {"time": 72095, "train": 22, "operation": 131}, {"time": 72172, "train": 19, "operation": 88}, {"time": 72174, "train": 19, "operation": 89}, {"time": 72178, "train": 20, "operation": 59}, {"time": 72265, "train": 18, "operation": 133}, {"time": 72270, "train": 22, "operation": 133}, {"time": 72395, "train": 21, "operation": 84}, {"time": 72491, "train": 22, "operation": 134}, {"time": 72590, "train": 21, "operation": 86}, {"time": 72592, "train": 21, "operation": 87}, {"time": 72622, "train": 19, "operation": 92}, {"time": 72623, "train": 26, "operation": 138}, {"time": 72624, "train": 19, "operation": 93}, {"time": 72810, "train": 26, "operation": 140}, {"time": 72850, "train": 20, "operation": 60}, {"time": 73017, "train": 20, "operation": 62}, {"time": 73035, "train": 21, "operation": 88}, {"time": 73037, "train": 21, "operation": 89}, {"time": 73077, "train": 26, "operation": 141}, {"time": 73128, "train": 18, "operation": 135}, {"time": 73140, "train": 22, "operation": 136}, {"time": 73168, "train": 22, "operation": 137}, {"time": 73174, "train": 22, "operation": 139}, {"time": 73193, "train": 26, "operation": 143}, {"time": 73200, "train": 22, "operation": 140}, {"time": 73299, "train": 19, "operation": 94}, {"time": 73345, "train": 18, "operation": 136}, {"time": 73402, "train": 20, "operation": 63}, {"time": 73494, "train": 21, "operation": 92}, {"time": 73519, "train": 20, "operation": 65}, {"time": 73581, "train": 19, "operation": 96}, {"time": 73695, "train": 21, "operation": 93}, {"time": 73859, "train": 18, "operation": 137}, {"time": 73859, "train": 18, "operation": 138}, {"time": 73954, "train": 22, "operation": 141}, {"time": 74099, "train": 26, "operation": 144}, {"time": 74214, "train": 26, "operation": 146}, {"time": 74256, "train": 22, "operation": 142}, {"time": 74451, "train": 21, "operation": 95}, {"time": 74558, "train": 20, "operation": 66}, {"time": 74619, "train": 22, "operation": 144}, {"time": 74704, "train": 20, "operation": 68}, {"time": 74815, "train": 19, "operation": 98}, {"time": 74954, "train": 26, "operation": 147}, {"time": 75048, "train": 22, "operation": 145}, {"time": 75049, "train": 19, "operation": 99}, {"time": 75099, "train": 22, "operation": 146}, {"time": 75125, "train": 26, "operation": 149}, {"time": 75211, "train": 21, "operation": 96}, {"time": 75211, "train": 22, "operation": 148}, {"time": 75541, "train": 20, "operation": 69}, {"time": 75674, "train": 20, "operation": 71}, {"time": 75867, "train": 26, "operation": 150}, {"time": 75976, "train": 26, "operation": 152}, {"time": 76036, "train": 19, "operation": 100}, {"time": 76280, "train": 26, "operation": 153}, {"time": 76300, "train": 26, "operation": 154}, {"time": 76306, "train": 26, "operation": 155}, {"time": 76312, "train": 22, "operation": 149}, {"time": 76389, "train": 19, "operation": 102}, {"time": 76422, "train": 26, "operation": 157}, {"time": 76424, "train": 26, "operation": 158}, {"time": 76424, "train": 26, "operation": 159}, {"time": 76445, "train": 20, "operation": 72}, {"time": 76489, "train": 22, "operation": 151}, {"time": 76569, "train": 21, "operation": 98}, {"time": 76606, "train": 20, "operation": 74}, {"time": 76815, "train": 21, "operation": 99}, {"time": 77151, "train": 20, "operation": 75}, {"time": 77176, "train": 22, "operation": 152}, {"time": 77273, "train": 20, "operation": 77}, {"time": 77308, "train": 22, "operation": 154}, {"time": 77345, "train": 19, "operation": 107}, {"time": 77347, "train": 19, "operation": 109}, {"time": 77360, "train": 19, "operation": 110}, {"time": 77529, "train": 19, "operation": 112}, {"time": 77742, "train": 19, "operation": 113}, {"time": 77890, "train": 21, "operation": 100}, {"time": 77908, "train": 20, "operation": 78}, {"time": 78081, "train": 20, "operation": 80}, {"time": 78319, "train": 21, "operation": 102}, {"time": 78404, "train": 22, "operation": 156}, {"time": 78423, "train": 19, "operation": 115}, {"time": 78448, "train": 20, "operation": 81}, {"time": 78451, "train": 19, "operation": 116}, {"time": 78459, "train": 19, "operation": 118}, {"time": 78486, "train": 19, "operation": 119}, {"time": 78654, "train": 22, "operation": 157}, {"time": 78735, "train": 20, "operation": 83}, {"time": 78749, "train": 20, "operation": 84}, {"time": 78751, "train": 20, "operation": 85}, {"time": 79194, "train": 20, "operation": 86}, {"time": 79196, "train": 20, "operation": 87}, {"time": 79215, "train": 19, "operation": 120}, {"time": 79242, "train": 22, "operation": 158}, {"time": 79242, "train": 22, "operation": 159}, {"time": 79425, "train": 21, "operation": 107}, {"time": 79427, "train": 21, "operation": 109}, {"time": 79442, "train": 21, "operation": 110}, {"time": 79504, "train": 19, "operation": 121}, {"time": 79627, "train": 21, "operation": 112}, {"time": 79637, "train": 20, "operation": 90}, {"time": 79639, "train": 20, "operation": 91}, {"time": 79864, "train": 21, "operation": 113}, {"time": 79877, "train": 19, "operation": 123}, {"time": 80279, "train": 20, "operation": 92}, {"time": 80282, "train": 19, "operation": 124}, {"time": 80333, "train": 19, "operation": 125}, {"time": 80445, "train": 19, "operation": 127}, {"time": 80546, "train": 20, "operation": 94}, {"time": 80622, "train": 21, "operation": 115}, {"time": 80652, "train": 21, "operation": 116}, {"time": 80660, "train": 21, "operation": 118}, {"time": 80688, "train": 21, "operation": 119}, {"time": 81465, "train": 19, "operation": 128}, {"time": 81473, "train": 21, "operation": 120}, {"time": 81631, "train": 19, "operation": 130}, {"time": 81703, "train": 20, "operation": 95}, {"time": 81795, "train": 21, "operation": 121}, {"time": 81985, "train": 20, "operation": 97}, {"time": 82231, "train": 21, "operation": 123}, {"time": 82289, "train": 19, "operation": 131}, {"time": 82410, "train": 19, "operation": 133}, {"time": 82649, "train": 21, "operation": 124}, {"time": 82700, "train": 21, "operation": 125}, {"time": 82814, "train": 21, "operation": 127}, {"time": 82925, "train": 20, "operation": 98}, {"time": 83271, "train": 20, "operation": 100}, {"time": 83419, "train": 19, "operation": 135}, {"time": 83660, "train": 19, "operation": 136}, {"time": 83997, "train": 21, "operation": 128}, {"time": 84168, "train": 20, "operation": 105}, {"time": 84170, "train": 20, "operation": 106}, {"time": 84184, "train": 21, "operation": 130}, {"time": 84244, "train": 19, "operation": 137}, {"time": 84244, "train": 19, "operation": 138}, {"time": 84876, "train": 21, "operation": 131}, {"time": 85011, "train": 21, "operation": 133}, {"time": 85249, "train": 20, "operation": 114}, {"time": 85255, "train": 20, "operation": 115}, {"time": 85985, "train": 20, "operation": 118}, {"time": 86208, "train": 21, "operation": 135}, {"time": 86263, "train": 20, "operation": 119}, {"time": 86474, "train": 21, "operation": 136}, {"time": 86606, "train": 20, "operation": 121}, {"time": 87005, "train": 20, "operation": 122}, {"time": 87056, "train": 20, "operation": 123}, {"time": 87110, "train": 21, "operation": 137}, {"time": 87110, "train": 21, "operation": 138}, {"time": 87168, "train": 20, "operation": 125}, {"time": 88206, "train": 20, "operation": 126}, {"time": 88385, "train": 20, "operation": 128}, {"time": 89102, "train": 20, "operation": 129}, {"time": 89234, "train": 20, "operation": 131}, {"time": 90291, "train": 20, "operation": 132}, {"time": 90542, "train": 20, "operation": 134}, {"time": 91158, "train": 20, "operation": 135}, {"time": 91158, "train": 20, "operation": 136}]}